Workbook

Sheet Pemetaan Kontrak 
C3: M: Mandatory
C4: O: Optional
C5: P: Pilihan
C6: X: Tidak Ada
C7: Status | D7: Kontrak Lumsum | H7: Kontrak Harga Satuan | K7: Kontrak Gabungan | N7: Kontrak Terima Jadi | Q7: Kontrak Kesepakatan Harga Satuan | T7: Kontrak Payung | U7: Kontrak Waktu Penugasan | V7: Kontrak Biaya Plus Imbalan
D8: Barang | E8: Jasa Lainnya | F8: Jasa Konsultansi | G8: Pekerjaan Konstruksi | H8: Barang | I8: Jasa Lainnya | J8: Pekerjaan Konstruksi | K8: Barang | L8: Jasa Lainnya | M8: Pekerjaan Konstruksi | N8: Barang | O8: Jasa Lainnya | P8: Pekerjaan Konstruksi | Q8: Barang | R8: Jasa Lainnya | S8: Pekerjaan Konstruksi | T8: Jasa Konsultansi | U8: Jasa Konsultansi | V8: Barang | W8: Jasa Lainnya | X8: Pekerjaan Konstruksi
B9: Identifier Perjanjian | C9: M | D9: TRUE | E9: TRUE | F9: TRUE | G9: TRUE | H9: TRUE | I9: TRUE | J9: TRUE | K9: TRUE | L9: TRUE | M9: TRUE | N9: TRUE | O9: TRUE | P9: TRUE | Q9: TRUE | R9: TRUE | S9: TRUE | T9: TRUE | U9: TRUE | V9: TRUE | W9: TRUE | X9: TRUE
B10: Dasar Pekerjaan | C10: M | D10: TRUE | E10: TRUE | F10: TRUE | G10: TRUE | H10: TRUE | I10: TRUE | J10: TRUE | K10: TRUE | L10: TRUE | M10: TRUE | N10: TRUE | O10: TRUE | P10: TRUE | Q10: TRUE | R10: TRUE | S10: TRUE | T10: TRUE | U10: TRUE | V10: TRUE | W10: TRUE | X10: TRUE
B11: Definisi | C11: M | D11: TRUE | E11: TRUE | F11: TRUE | G11: TRUE | H11: TRUE | I11: TRUE | J11: TRUE | K11: TRUE | L11: TRUE | M11: TRUE | N11: TRUE | O11: TRUE | P11: TRUE | Q11: TRUE | R11: TRUE | S11: TRUE | T11: TRUE | U11: TRUE | V11: TRUE | W11: TRUE | X11: TRUE
B12: Ruang Lingkup Pekerjaan/Perjanjian | C12: M | D12: TRUE | E12: TRUE | F12: TRUE | G12: TRUE | H12: TRUE | I12: TRUE | J12: TRUE | K12: TRUE | L12: TRUE | M12: TRUE | N12: TRUE | O12: TRUE | P12: TRUE | Q12: TRUE | R12: TRUE | S12: TRUE | T12: TRUE | U12: TRUE | V12: TRUE | W12: TRUE | X12: TRUE
B13: Metodologi dan Tahapan Pelaksanaan Pekerjaan | C13: O | D13: TRUE | E13: TRUE | F13: TRUE | G13: TRUE | H13: TRUE | I13: TRUE | J13: TRUE | K13: TRUE | L13: TRUE | M13: TRUE | N13: TRUE | O13: TRUE | P13: TRUE | Q13: TRUE | R13: TRUE | S13: TRUE | T13: TRUE | U13: TRUE | V13: TRUE | W13: TRUE | X13: TRUE
B14: Nilai Perjanjian | C14: M | D14: TRUE | E14: TRUE | F14: TRUE | G14: TRUE | H14: TRUE | I14: TRUE | J14: TRUE | K14: TRUE | L14: TRUE | M14: TRUE | N14: TRUE | O14: TRUE | P14: TRUE | Q14: TRUE | R14: TRUE | S14: TRUE | T14: TRUE | U14: TRUE | V14: TRUE | W14: TRUE | X14: TRUE
B15: KHS | C15: P | D15: FALSE | E15: FALSE | F15: FALSE | G15: FALSE | H15: FALSE | I15: FALSE | J15: FALSE | K15: FALSE | L15: FALSE | M15: FALSE | N15: FALSE | O15: FALSE | P15: FALSE | Q15: TRUE | R15: TRUE | S15: TRUE | T15: TRUE | U15: FALSE | V15: FALSE | W15: FALSE | X15: FALSE
B16: Harga Satuan | C16: P | D16: FALSE | E16: FALSE | F16: FALSE | G16: FALSE | H16: TRUE | I16: TRUE | J16: TRUE | K16: FALSE | L16: FALSE | M16: FALSE | N16: FALSE | O16: FALSE | P16: FALSE | Q16: FALSE | R16: FALSE | S16: FALSE | T16: FALSE | U16: FALSE | V16: FALSE | W16: FALSE | X16: FALSE
B17: Non Harga Satuan | C17: P | D17: TRUE | E17: TRUE | F17: TRUE | G17: TRUE | H17: FALSE | I17: FALSE | J17: FALSE | K17: TRUE | L17: TRUE | M17: TRUE | N17: TRUE | O17: TRUE | P17: TRUE | Q17: FALSE | R17: FALSE | S17: FALSE | T17: FALSE | U17: TRUE | V17: FALSE | W17: FALSE | X17: FALSE
B18: Cost + Fee | C18: P | D18: FALSE | E18: FALSE | F18: FALSE | G18: FALSE | H18: FALSE | I18: FALSE | J18: FALSE | K18: FALSE | L18: FALSE | M18: FALSE | N18: FALSE | O18: FALSE | P18: FALSE | Q18: FALSE | R18: FALSE | S18: FALSE | T18: FALSE | U18: FALSE | V18: TRUE | W18: TRUE | X18: TRUE
B19: Struktur Organisasi Pelaksanaan | C19: M | D19: TRUE | E19: TRUE | F19: TRUE | G19: TRUE | H19: TRUE | I19: TRUE | J19: TRUE | K19: TRUE | L19: TRUE | M19: TRUE | N19: TRUE | O19: TRUE | P19: TRUE | Q19: TRUE | R19: TRUE | S19: TRUE | T19: TRUE | U19: TRUE | V19: TRUE | W19: TRUE | X19: TRUE
B20: Jangka Waktu | C20: M | D20: TRUE | E20: TRUE | F20: TRUE | G20: TRUE | H20: TRUE | I20: TRUE | J20: TRUE | K20: TRUE | L20: TRUE | M20: TRUE | N20: TRUE | O20: TRUE | P20: TRUE | Q20: TRUE | R20: TRUE | S20: TRUE | T20: TRUE | U20: TRUE | V20: TRUE | W20: TRUE | X20: TRUE
... B65: Penutup | C65: M | D65: TRUE | E65: TRUE | F65: TRUE | G65: TRUE | H65: TRUE | I65: TRUE | J65: TRUE | K65: TRUE | L65: TRUE | M65: TRUE | N65: TRUE | O65: TRUE | P65: TRUE | Q65: TRUE | R65: TRUE | S65: TRUE | T65: TRUE | U65: TRUE | V65: TRUE | W65: TRUE | X65: TRUE

Sheet Master Klausul
B1: Klausul | C1: Data
A2: Header | B2: Perjanjian/Kontrak [Nomor Perjanjian/Kontrak] tentang [Nama Pekerjaan] Antara PT PLN (Persero) dengan [Nama Penyedia Barang/Jasa] | C2: Nomor Perjanjian/Kontrak
C3: Nama Pekerjaan
C4: Nama Penyedia Barang/Jasa
A5: ='Pemetaan Kontrak '!B9 -> Identifier Perjanjian | B5: Perjanjian [Nama Pekerjaan] berikut semua lampirannya dibuat dan disepakati di [Tempat Perjanjian/Kontrak] pada hari [Hari Penandatanganan] tanggal [Tanggal Penandatanganan] oleh dan antara: I. PT PLN (Persero) : Suatu Perseroan Terbatas yang didirikan berdasarkan hukum Republik Indonesia berdasarkan Akta Nomor 169 tanggal 30 Juli 1994, dibuat oleh dan dihadapan Sutjipto, S.H. Notaris di Jakarta, yang telah diubah beberapa kali, terakhir dilakukan perubahan sebagaimana Akta No. [No Akta Perubahan Terakhir] tanggal [tanggal Akta] dibuat oleh dan dihadapan [Notaris]. Notaris di Jakarta, yang dalam hal ini di wakili oleh [Nama pejabat yang menandatangani] selaku [Jabatan Penandatangan] PT PLN (Persero) [Nama Unit] berdasarkan Keputusan Direksi PT PLN (Persero) Nomor: [Nomor SK] tentang [Judul SK], sehingga dalam hal ini berhak dan berwenang bertindak untuk dan atas nama PT PLN (Persero)[Nama Unit], berkedudukan di [Alamat Unit], untuk selanjutnya disebut sebagai PIHAK PERTAMA II. [Nama Penyedia Barang/Jasa] : Suatu [Bentuk Badan Usaha] yang didirikan berdasarkan Hukum Republik Indonesia berdasarkan Akta No. [Nomor Akta Pendirian Perusahaan] tanggal [Tanggal Akta Pendirian] dibuat oleh dan dihadapan [Nama Notaris Pembuat Akta], Notaris di [Kota Notaris], yang telah diubah beberapa kali, terakhir dilakukan perubahan sebagaimana Akta Nomor [Nomor Akta Perubahan Terakhir] tanggal [Tanggal Perubahan Terakhir] dibuat oleh dan dihadapan [Nama Notaris Pembuat Akta], Notaris di [Kota Notaris] yang dalam hal ini diwakili oleh [Nama perwakilan perusahaan] selaku [Jabatan perwakilan] sehingga dalam hal ini berhak dan bewenang bertindak untuk dan atas nama [Nama Penyedia Barang/Jasa], berkedudukan di [Alamat/Kota Domisili Penyedia Barang/Jasa], untuk selanjutnya disebut sebagai PIHAK KEDUA Untuk selanjutnya PIHAK PERTAMA dan PIHAK KEDUA secara sendiri-sendiri disebut PIHAK dan secara Bersama-sama disebut PARA PIHAK. | C5: Nama Pekerjaan
C6: Tempat Perjanjian/Kontrak
C7: Hari penandatanganan
C8: Tanggal Penandatanganan
C9: No Akta Perubahan Terakhir
C10: tanggal Akta
C11: Notaris
C12: Nama pejabat yang menandatangani
C13: Jabatan Penandatangan
C14: Nama Unit
C15: Nomor SK
C16: Judul SK
C17: Alamat Unit
... C27: Alamat/kota domisili Penyedia Barang/Jasa
A28: ='Pemetaan Kontrak '!B10 -> Dasar Pekerjaan | B28: 1. PIHAK PERTAMA dalam menjalankan kegiatan operasionalnya, melakukan [jenis pengadaan] dengan mengacu pada: a. [list] Peraturan 2. PIHAK KEDUA telah menyetujui untuk melaksanakan pekerjaan [Jenis Pengadaan] sesuai dengan persyaratan dan ketentuan dalam Perjanjian/Kontrak ini sesuai dengan dokumen-dokumen sebagaimana berikut: a. Dokumen Tender/RKS No. [Nomor dokumen tender/RKS], tanggal [Tanggal dokumen tender/RKS] beserta addendumnya [apabila ada]. b. Surat Penawaran Sampul 1 (Administrasi dan Teknis) No. [Nomor surat administrasi & teknis] tanggal [Tanggal surat penawaran sampul 1] c. Surat Penawaran Sampul 2 (Harga) No. [Nomor surat penawaran harga] tanggal [Tanggal surat penawaran sampul 2] d. Surat Penunjukan Penyedia Barang/Jasa No. [Nomor SPPBJ/SPPBJ] tanggal [Tanggal surat penunjukan] e. Surat Perintah Mulai Kerja No. [Nomor Surat Perintah Mulai Kerja] tanggal [Tanggal Surat Perintah Mulai Kerja] f. Kesepakatan Diskusi Perjanjian/Kontrak (Contract Discussion Agreement) tanggal [Tanggal Contract Discussion Agreement] g. [Dokumen pendukung tambahan (jika dibutuhkan)] Berdasarkan hal-hal tersebut, maka PARA PIHAK dengan ini sepakat untuk mengikatkan diri dalam sebuah Perjanjian/Kontrak yang berisi syarat-syarat dan ketentuan-ketentuan sebagai berikut: | C28: [list] Peraturan
C29: Jenis Pengadaan
C30: Nomor Dokumen Tender/RKS
C31: Tanggal Dokumen Tender/RKS
C32: Nomor surat administrasi & teknis
C33: Tanggal surat penawaran sampul 1
C34: Nomor surat penawaran harga
C35: Tanggal surat penawaran sampul 2
C36: Nomor SPPBJ/SPPBJ
C37: Tanggal surat penunjukan
C38: Nomor Surat Perintah Mulai Kerja
C39: Tanggal Surat Perintah Mulai Kerja
C40: Tanggal Contract Discussion Agreement
C41: Dokumen pendukung tambahan (jika dibutuhkan)
A42: ='Pemetaan Kontrak '!B11 -> Definisi | B42: 1. Berita Acara Serah Terima Pekerjaan (BASTP) adalah berita acara yang dibuat setelah progres fisik pekerjaan mencapai 100% (seratus persen). 2. Berita Acara Penyerahan Akhir (BAP-Akhir) adalah berita acara yang dibuat untuk menyatakan Hak dan Kewajiban para pihak telah selesai seluruhnya sehingga Perjanjian dinyatakan ditutup. 3. Direksi Pekerjaan adalah Pejabat yang diberi wewenang untuk mengawasi pelaksanaan pekerjaan berdasarkan Perjanjian/Kontrak. [mengikuti definisi tercantum dalam Perdir Nomor 0018.P/DIR/2023 dan sesuai jenis Pengadaan] | C42: Mengikuti definisi tercantum dalam Perdir Nomor 0018.P/DIR/2023 dan sesuai jenis Pengadaan
A43: ='Pemetaan Kontrak '!B12 -> Ruang Lingkup Pekerjaan/Perjanjian | B43: 1. PIHAK PERTAMA memberikan pekerjaan kepada PIHAK KEDUA untuk melaksanakan [Jenis Pengadaan] [Nama Pekerjaan] dan PIHAK KEDUA menerima penugasan tersebut. 2. Uraian [Jenis Pengadaan] tersebut di atas tercantum sebagaimana Lampiran 1 ini dan/atau sesuai dengan Dokumen Pengadaan yang telah ditentukan PIHAK PERTAMA. | C43: Jenis Pengadaan
C44: Nama Pekerjaan
A45: ='Pemetaan Kontrak '!B13 -> Metodologi dan Tahapan Pelaksanaan Pekerjaan | B45: 1. | C45: Freetext
A46: ='Pemetaan Kontrak '!B14 -> Nilai Perjanjian
A47: KHS | B47: 1. Sumber dana yang digunakan dalam pelaksanaan Pekerjaan Perjanjian/Kontrak adalah [APLN/Pinjaman/Hibah Luar Negeri/Pinjaman/Hibah Dalam Negeri]. 2. Harga Satuan adalah sebagaimana ditetapkan pada Perjanjian/Kontrak ini berlaku dan mengikat Para Pihak untuk jangka waktu 1 (satu) tahun atau sepanjang Jangka Waktu Penerbitan. 3. Jenis Perjanjian/Kontrak untuk pekerjaan ini adalah [Jenis Perjanjian/Kontrak]. | C47: Sumber Dana [APLN/Pinjaman/Hibah Luar Negeri/Pinjaman/Hibah Dalam Negeri]
C48: Jenis Perjanjian/Kontrak
A49: Harga Satuan | B49: 1. Sumber dana yang digunakan dalam pelaksanaan Pekerjaan Perjanjian/Kontrak adalah [APLN/Pinjaman/Hibah Luar Negeri/Pinjaman/Hibah Dalam Negeri]. 2. Harga Satuan adalah sebagaimana ditetapkan pada Perjanjian/Kontrak ini berlaku dan mengikat Para Pihak untuk jangka waktu 1 (satu) tahun atau sepanjang Jangka Waktu Penerbitan. 3. PIHAK KEDUA akan melaksanakan Pekerjaan sesuai dengan spesifikasi pada ayat (1) Pasal ini dengan mempertimbangkan volume dan satuan lainnya bersifat indikatif sesuai dengan Lampiran 1 Perjanjian ini. 4. Jenis Perjanjian/Kontrak untuk pekerjaan ini adalah [Jenis Perjanjian/Kontrak]. | C49: Sumber Dana [APLN/Pinjaman/Hibah Luar Negeri/Pinjaman/Hibah Dalam Negeri]
C50: Jenis Perjanjian/Kontrak
A51: ='Pemetaan Kontrak '!B17 -> Non Harga Satuan | B51: 1. Sumber dana yang digunakan dalam pelaksanaan Pekerjaan Perjanjian/Kontrak adalah [APLN/Pinjaman/Hibah Luar Negeri/Pinjaman/Hibah Dalam Negeri]. 2. Nilai Total Perjanjian/Kontrak untuk Pekerjaan [Nama Pekerjaan] ini adalah sebagaimana dirinci dibawah ini a. Nilai Perjanjian/Kontrak : [mata uang yang disepakati oleh Para Pihak][Nilai nominal Perjanjian/Kontrak] ([terbilang]) Nilai tukar [Mata uang yang disepakati oleh Para Pihak] yang digunakan sebagai Nilai Perjanjian/Kontrak ditetapkan berdasarkan [Kurs tengah/JISDOR dari Bank Indonesia] yang berlaku pada tanggal [Tanggal kurs yang digunakan]; b. Pajak Pertambahan Nilai [Persentase Pajak]% dari Nilai Perjanjian/Kontrak : [mata uang yang disepakati oleh Para Pihak] [Nilai PPN nominal] ([terbilang]). Nilai Total Perjanjian/Kontrak : [Rp/USD/mata uang yang disepakati oleh Para Pihak][Total nilai Perjanjian/Kontrak setelah pajak] ([terbilang]) 3. Jenis Perjanjian/Kontrak untuk pekerjaan ini adalah [Jenis Perjanjian/Kontrak]. | C51: Sumber Dana [APLN/Pinjaman/Hibah Luar Negeri/Pinjaman/Hibah Dalam Negeri]
C52: Nama Pekerjaan
C53: Mata uang
C54: Nilai nominal Perjanjian/Kontrak
C55: Kurs tengah/JISDOR dari Bank Indonesia
C56: Tanggal kurs yang digunakan
C57: Persentase
C58: Persentase Pajak
C59: Nilai PPN Nominal
C60: Total nilai Perjanjian/Kontrak setelah pajak
C61: Jenis Perjanjian/Kontrak
A62: ='Pemetaan Kontrak '!B18 -> Cost + Fee | B62: 1. Sumber dana yang digunakan dalam pelaksanaan Pekerjaan Perjanjian adalah [Anggaran APLN/Pinjaman/Hibah Luar Negeri/Pinjaman/Hibah Dalam Negeri]. 2. Nilai Total Perjanjian untuk Pekerjaan [Nama Pekerjaan] ini adalah sebagaimana dirinci dibawah ini: a. Biaya Aktual Perjanjian, yaitu biaya yang dikeluarkan sesuai dengan pengeluaran sebenarnya dalam pelaksanaan pekerjaan dalam Perjanjian ini. b. Imbalan : [Persen Imbalan]% dari Biaya Aktual Perjanjian atau sebesar [mata uang yang disepakati oleh Para Pihak][Nilai Nominal Total] ([terbilang]) atau [mata uang yang disepakati oleh Para Pihak][Nilai Nominal] ([terbilang]) c. Pajak Pertambahan Nilai [Persen Pajak]% dari Nilai Total Perjanjian : [mata uang yang disepakati oleh Para Pihak ] [Nilai Nominal Total] ([terbilang]) 3. Jenis Perjanjian/Kontrak untuk pekerjaan ini adalah [Jenis Perjanjian/Kontrak]. | C62: Sumber Dana [APLN/Pinjaman/Hibah Luar Negeri/Pinjaman/Hibah Dalam Negeri]
C63: Nama Pekerjaan
C64: Persen Imbalan
C65: Mata uang
C66: Nilai nominal Total
C67: Nilai nominal
C68: Persen Pajak
C69: Jenis Perjanjian/Kontrak
A70: ='Pemetaan Kontrak '!B19 -> Struktur Organisasi Pelaksanaan | B70: 1. PIHAK PERTAMA menunjuk [Nama Jabatan] [Nama Unit] sebagai Direksi Pekerjaan untuk melakukan pengendalian dan pengawasan pelaksanaan dan/atau penyerahan pekerjaan serta bertanggungjawab untuk menyelesaikan semua administrasi, dan semua Berita Acara yang diperlukan terkait dengan proses tagihan (pembayaran) yang berkaitan dengan Perjanjian/Kontrak ini. 2. Apabila petugas yang ditunjuk tersebut dalam Ayat 1 Pasal ini berhalangan atau tidak dapat menjalankan kewajibannya, maka PIHAK PERTAMA akan menunjuk penggantinya dan akan disampaikan kepada PIHAK KEDUA secara tertulis. 3. Direksi Pekerjaan berhak untuk memberikan petunjuk-petunjuk/pengarahan kepada PIHAK KEDUA dalam melaksanakan pekerjaan sehari-hari. | C70: Nama Jabatan
C71: Nama Unit
A72: ='Pemetaan Kontrak '!B20 -> Jangka Waktu | B72: 1. Jangka waktu pelaksanaan [Jenis Pengadaan] yang diatur dalam Pasal [Nomor pasal yang mengatur ruang lingkup/ketentuan pekerjaan] Perjanjian/Kontrak ini harus diselesaikan oleh PIHAK KEDUA paling lambat [durasi pelaksanaan Perjanjian/Kontrak] Hari Kalender, dihitung mulai dari [tanggal penandatanganan Perjanjian/Kontrak ini/tanggal penyerahan Jaminan Pelaksanaan oleh PIHAK KEDUA kepada PIHAK PERTAMA], yaitu tanggal [Tanggal mulai efektif pelaksanaan]. 2. Apabila diperlukan, Perjanjian/Kontrak ini dapat diperpanjang oleh PARA PIHAK melalui kesepakatan bersama sebelum berakhirnya periode Perjanjian/Kontrak. Perpanjangan tersebut akan dituangkan dalam bentuk amandemen atau dokumen tertulis lainnya. 3. Pihak yang ingin memperpanjang Perjanjian/Kontrak harus mengirimkan pemberitahuan tertulis yang disertai dengan penjelasan yang rinci kepada pihak lainnya tidak lebih dari [jumlah hari batas perpanjangan] Hari Kalender sebelum Perjanjian/Kontrak berakhir. Pihak lainnya harus memberikan keputusan mengenai persetujuan perpanjangan Perjanjian/Kontrak dalam waktu [jumlah hari Tenggat pemberian keputusan persetujuan] Hari Kalender. Jika tidak ada keputusan persetujuan perpanjangan Perjanjian/Kontrak dalam jangka waktu yang ditentukan dalam ayat ini, maka Perjanjian/Kontrak akan dianggap berakhir. | C72: Jenis pengadaan
C73: Nomor pasal yang mengatur ruang lingkup/ketentuan pekerjaan
C74: Durasi Pelaksanaan Perjanjian/Kontrak
C75: Tanggal penandatanganan Perjanjian/Kontrak ini/tanggal penyerahan Jaminan Pelaksanaan oleh PIHAK KEDUA kepada PIHAK PERTAMA
C76: Tanggal mulai efektif pelaksanaan
C77: jumlah hari batas perpanjangan
C78: jumlah hari Tenggat pemberian keputusan persetujuan
A79: ='Pemetaan Kontrak '!B21 -> Hak, Kewajiban, dan Larangan | B79: 1. Hak PIHAK PERTAMA dalam pelaksanaan Perjanjian/Kontrak: a. PIHAK PERTAMA berhak mendapatkan hasil pekerjaan yang dilaksanakan oleh PIHAK KEDUA dengan kualitas dan kuantitas sesuai dengan ditentukan oleh PIHAK PERTAMA dalam Perjanjian/Kontrak ini. b. PIHAK PERTAMA berhak mendapatkan hasil pekerjaan dari PIHAK KEDUA sesuai dengan jangka waktu pelaksanaan pekerjaan yang diatur sebagaimana pada Pasal [Nomor pasal] Perjanjian/Kontrak ini. c. PIHAK PERTAMA berhak meminta kepada PIHAK KEDUA tenaga kerja yang memiliki keahlian dan keterampilan di bidangnya untuk melaksanakan pekerjaan. d. PIHAK PERTAMA berhak mengenakan sanksi kepada PIHAK KEDUA apabila PIHAK KEDUA tidak dapat melaksanakan ketentuan-ketentuan dalam Perjanjian/Kontrak ini. e. PIHAK PERTAMA berhak memutus Perjanjian/Kontrak ini secara sepihak apabila PIHAK KEDUA tidak dapat melaksanakan ketentuan-ketentuan dalam Perjanjian/Kontrak ini. 2. Kewajiban PIHAK PERTAMA dalam pelaksanaan Perjanjian/Kontrak: a. PIHAK PERTAMA wajib melakukan pembayaran berupa biaya aktual dan imbalan kepada PIHAK KEDUA atas hasil pelaksanaan pekerjaan yang telah dilaksanakan oleh PIHAK KEDUA sesuai dengan Perjanjian/Kontrak. b. PIHAK PERTAMA wajib memberikan instruksi dan/atau arahan kepada PIHAK KEDUA terkait pelaksanaan pekerjaan. 3. Hak PIHAK KEDUA dalam pelaksanaan Perjanjian/Kontrak: a. PIHAK KEDUA berhak menerima pembayaran berupa biaya aktual dan imbalan dari PIHAK PERTAMA atas hasil pelaksanaan yang telah dilaksanakan oleh PIHAK KEDUA. b. PIHAK KEDUA berhak menerima instruksi dan/atau arahan dari PIHAK PERTAMA sesuai jadwal pelaksanaan pekerjaan kepada PIHAK KEDUA terkait pelaksanaan pekerjaan yang telah ditetapkan dalam Perjanjian/Kontrak. 4. Kewajiban PIHAK KEDUA dalam pelaksanaan Perjanjian/Kontrak: a. PIHAK KEDUA wajib melaksanakan dan menyelesaikan pekerjaan dengan kualitas dan kuantitas sesuai dengan uraian pekerjaan yang telah diatur dalam Perjanjian/Kontrak ini. b. PIHAK KEDUA wajib menyelesaikan dan menyerahkan hasil pekerjaan sesuai dengan jangka waktu pelaksanaan pekerjaan yang diatur sebagaimana pada Pasal [Nomor pasal yang mengatur jangka waktu pelaksanaan] Perjanjian/Kontrak ini. c. PIHAK KEDUA wajib membuat dan menyampaikan kepada PIHAK PERTAMA laporan hasil pekerjaan. d. PIHAK KEDUA wajib melaksanakan ketentuan Keselamatan dan Kesehatan Kerja (K3) serta Pengamanan sebagaimana diatur pada Perjanjian/Kontrak ini. e. PIHAK KEDUA wajb melaksanakan ketentuan kelestarian lingkungan dan fasilitas sebagaimana diatur pada Perjanjian/Kontrak ini. f. PIHAK KEDUA wajib menggunakan tenaga kerja yang memiliki keahlian dan keterampilan di bidangnya untuk melaksanakan pekerjaan. g. PIHAK KEDUA bertanggung jawab dalam mendapatkan seluruh izin-izin yang diperlukan untuk kelancaran pekerjaan dan seluruh biaya yang timbul menjadi tanggung jawab PIHAK KEDUA. | C79: Nomor pasal
A80: ='Pemetaan Kontrak '!B22 -> Pola Pengawasan | B80: 1. PIHAK PERTAMA berhak melakukan pengawasan terhadap pelaksanaan Pekerjaan yang diwakili oleh Direksi Pekerjaan dibantu oleh Pengawas Pekerjaan. 2. Direksi Pekerjaan melakukan pemeriksaan atas Pekerjaan yang telah diserahkan oleh PIHAK KEDUA kepada PIHAK PERTAMA dengan melakukan pengendalian pelaksanaan Pekerjaan di lapangan, agar pelaksanaan Pekerjaan sesuai dengan ruang lingkup Perjanjian/Kontrak ini sebagaimana Lampiran 1. 3. Direksi Pekerjaan akan menyusun detil pelaksanaan Pekerjaan yang meliputi uraian Pekerjaan beserta jangka waktu dari masing-masing uraian Pekerjaan. 4. Apabila dalam pemeriksaan pekerjaan terdapat rusak/cacat atau tidak sesuai dengan syarat yang telah ditentukan, maka Direksi Pekerjaan memberitahukan secara tertulis kepada PIHAK KEDUA selambat-lambatnya [jumlah hari Tenggat waktu pemberitahuan ketidaksesuaian/cacat pekerjaan] ([terbilang]) Hari Kalender sejak diketahui adanya ketidaksesuaian dengan syarat yang ditentukan. 5. PIHAK KEDUA diberikan kesempatan untuk melakukan perbaikan Pekerjaan sebagaimana dimaksud ayat (4) Pasal ini dalam jangka waktu selambat-lambatnya [jumlah hari Waktu perbaikan pekerjaan oleh PIHAK KEDUA] Hari Kalender sejak PIHAK KEDUA menerima pemberitahuan tertulis dari PIHAK PERTAMA. | C80: Jumlah Hari Tenggat waktu pemberitahuan ketidaksesuaian/cacat pekerjaan
C81: Jumlah Hari Waktu perbaikan pekerjaan oleh PIHAK KEDUA
A82: ='Pemetaan Kontrak '!B23 -> Manajemen Mutu dan Sistem Verifikasi Kepatuhan | B82: 1. PIHAK KEDUA wajib menjamin bahwa seluruh produk dan layanan yang disediakan sesuai dengan standar mutu yang telah disepakati dalam Perjanjian/Kontrak ini. 2. PIHAK KEDUA wajib memiliki dan menjalankan Sistem Manajemen Mutu dengan standar internasional (seperti ISO 9001) untuk memastikan kepatuhan terhadap persyaratan mutu yang berlaku. 3. PIHAK KEDUA wajib memberikan akses kepada PIHAK PERTAMA untuk melakukan verifikasi kepatuhan terhadap standar mutu yang telah ditetapkan. 4. Verifikasi kepatuhan dapat dilakukan melalui audit, inspeksi atau metode verifikasi lainnya yang telah disepakati oleh PARA PIHAK. | C82: -
A83: ='Pemetaan Kontrak '!B24 -> Hasil dan Laporan | B83: Hasil pekerjaan atas Perjanjian/Kontrak ini yang harus diserahkan kepada PIHAK KEDUA kepada PIHAK PERTAMA adalah sebagai berikut: 1. | C83: Freetext
A84: ='Pemetaan Kontrak '!B25 -> Lokasi Pekerjaan | B84: Lokasi pelaksanaan atau tempat penyerahan hasil pekerjaan adalah di PT PLN (Persero) [Nama Unit], [Alamat Unit] | C84: Nama Unit
C85: Alamat Unit
A86: ='Pemetaan Kontrak '!B26 -> Jaminan
A87: ='Pemetaan Kontrak '!B27 -> Jaminan Uang Muka | B87: 1. Jaminan Uang Muka adalah sebesar [nominal yang minimal sama dengan nilai uang muka yang dibayarkan PIHAK PERTAMA kepada PIHAK KEDUA]. 2. Jaminan Uang Muka ditetapkan untuk menjamin kelancaran pembiayaan pekerjaan yang akan dilakukan oleh PIHAK KEDUA. 3. Masa berlaku Jaminan Uang Muka berlaku sejak tanggal pembayaran uang muka oleh PIHAK PERTAMA kepada PIHAK KEDUA sampai dengan tanggal [tanggal pelunasan uang muka] yang telah ditetapkan oleh PARA PIHAK. | C87: [nominal Jaminan Uang Muka]
C88: Tanggal pelunasan uang muka
A89: ='Pemetaan Kontrak '!B28 -> Jaminan Pelaksanaan | B89: 1. Jaminan Pelaksanaan diserahkan dari PIHAK KEDUA kepada PIHAK PERTAMA paling lambat 14 (empat belas) hari kerja setelah Perjanjian/Kontrak ditandatangani dan menjadi syarat efektif Perjanjian/Kontrak ini. 2. Apabila sampai dengan batas waktu yang ditetapkan, Jaminan Pelaksanaan belum diserahkan, maka Perjanjian ini dapat dibatalkan sepihak oleh PIHAK PERTAMA, dan PIHAK KEDUA yang ditunjuk dapat dikenakan sanksi Daftar Hitam (Blacklist) serta Jaminan Penawaran (jika ada) dicairkan dan menjadi milik PIHAK PERTAMA. 3. Jaminan Pelaksanaan dari Bank Umum (tidak termasuk Bank Perkreditan Rakyat) atau bank asing yang beroperasi di Indonesia/mempunyai perwakilan di Indonesia atau Lembaga Pembiayaan Ekspor Indonesia dan bukan yang diterbitkan oleh Perusahaan Asuransi yang terdapat dalam Daftar Penerbit Jaminan Terseleksi seperti terlampir, atas nama Perusahaan yang menawarkan, ditujukan kepada PT PLN (Persero) Kantor Pusat [Nama Unit], [Alamat Unit]. 4. Jaminan pelaksanaan sebesar minimal 5% (lima persen) dari nilai Perjanjian/Kontrak ini. 5. Masa berlaku Jaminan Pelaksanaan sejak tanggal diterbitkannya Jaminan sampai dengan sekurang-kurangnya waktu Serah Terima Pekerjaan Pertama dengan masa klaim selambat-lambatnya 14 (empat belas) hari setelah berakhirnya Jaminan Pelaksanaan. 6. Jaminan Pelaksanaan menjadi milik PIHAK PERTAMA dalam hal: 6.1. PIHAK KEDUA mengundurkan diri setelah menandatangani surat Perjanjian/Kontrak. 6.2. PIHAK KEDUA dalam waktu yang telah ditetapkan tidak melaksanakan/menyelesaikan pekerjaan atau terjadi pemutusan Perjanjian/Kontrak yang diakibatkan kelalaian PIHAK KEDUA. 7. Jaminan Pelaksanaan dapat dikembalikan setelah waktu Serah Terima Pekerjaan. 8. Jaminan Pelaksanaan bersifat tanpa syarat (unconditional) dan tidak dapat dialihkan (non-transferable). 9. Jaminan Pelaksanaan dicairkan dan menjadi milik PIHAK PERTAMA apabila dilakukan pemutusan Perjanjian/Kontrak. 10. Dalam hal pelaksanaan pekerjaan belum selesai dan memerlukan perpanjangan waktu pelaksanaan, maka PIHAK KEDUA wajib bersedia untuk memperpanjang masa berlaku Jaminan Pelaksanaan. 11. Dalam hal PIHAK KEDUA tidak bersedia memperpanjang masa berlaku Jaminan Pelaksanaan, maka PIHAK KEDUA tersebut dianggap wanprestasi dan Jaminan Pelaksanaan dicairkan dan menjadi milik PIHAK PERTAMA. | C89: Nama Unit
C90: Alamat Unit
A91: ='Pemetaan Kontrak '!B29 -> Jaminan Pemeliharaan | B91: 1. Format Jaminan Pemeliharaan sesuai dengan format yang ditetapkan oleh Penerbit Jaminan. 2. PIHAK KEDUA wajib menyerahkan Jaminan Pemeliharaan kepada PIHAK PERTAMA, minimal [nilai Persen]% [nilai Jaminan] dari Nilai Perjanjian/Kontrak, paling lambat diserahkan pada saat Berita Acara Serah Terima Pekerjaan ditandatangani dan menjadi syarat efektif untuk pembayaran. 3. Masa Pemeliharaan adalah [Jumlah Bulan] bulan sejak tanggal ditandatanganinya Berita Acara Serah Terima Pekerjaan. 4. Jaminan Pemeliharaan ditetapkan untuk menjamin kualitas Pekerjaan yang diserahkan, dipersyaratkan untuk pekerjaan yang memerlukan Masa Pemeliharaan. 5. PIHAK PERTAMA menerima akhir pekerjaan setelah PIHAK KEDUA melaksanakan semua kewajibannya selama Masa Pemeliharaan dengan baik yang dibuktikan dengan penandatanganan Berita Acara Selesainya Masa Pemeliharaan. 6. Masa berlaku Jaminan Pemeliharaan adalah sejak tanggal penerbitan Jaminan Pemeliharaan sampai dengan tanggal Berita Acara Selesainya Masa Pemeliharaan. 7. Selama Masa Pemeliharaan, PIHAK KEDUA harus menjaga dan mempertahankan hasil pekerjaan yang telah dilaksanakan sehingga tetap seperti kondisi pada saat dilakukan serah terima pekerjaan sebagaimana Berita Acara Serah Terima Pekerjaan (BASTP). 8. Apabila selama Masa Pemeliharaan terdapat kerusakan terhadap hasil pekerjaan maka PIHAK KEDUA harus melaksanakan perbaikan pekerjaan sehingga hasil pekerjaan sesuai dengan spesifikasi material dan syarat-syarat teknis sebagaimana telah ditentukan oleh PIHAK PERTAMA. 9. Apabila selama Masa Pemeliharaan telah selesai dan PIHAK KEDUA telah melaksanakan apa yang menjadi kewajibannya selama Masa Pemeliharaan, maka PIHAK KEDUA mengajukan secara tertulis kepada PIHAK PERTAMA untuk dilakukan penyerahan akhir pekerjaan. 10. Sebelum dilakukan penyerahan akhir pekerjaan, atau Direksi Pekerjaan akan melakukan pemeriksaan terhadap hasil pekerjaan yang dilakukan oleh PIHAK KEDUA selama masa pemeliharaan ini. Apabila hasil pemeriksaan pengawas pekerjaan dan/atau Direksi Pekerjaan terhadap hasil pekerjaan PIHAK KEDUA telah sesuai sebagaimana dimaksud pada Perjanjian/Kontrak ini, maka PIHAK PERTAMA akan menerima penyerahan akhir pekerjaan tersebut yang dituangkan dalam Berita Acara Penyerahan Akhir Pekerjaan yang ditandatangani oleh PARA PIHAK dan Direksi Pekerjaan. | C91: Nilai Persen
C92: Nilai Jaminan
C93: Jumlah Bulan Pemeliharaan
A94: ='Pemetaan Kontrak '!B30 -> Retensi | B94: 1. Selama Masa Pemeliharaan, PIHAK KEDUA harus menjaga dan mempertahankan hasil pekerjaan yang telah dilaksanakan sehingga tetap seperti kondisi pada saat dilakukan serah terima pekerjaan sebagaimana Berita Acara Serah Terima Pekerjaan (BASTP). 2. Apabila selama Masa Pemeliharaan terdapat kerusakan terhadap hasil pekerjaan maka PIHAK KEDUA harus melaksanakan perbaikan pekerjaan sehingga hasil pekerjaan sesuai dengan spesifikasi material dan syarat-syarat teknis sebagaimana telah ditentukan oleh PIHAK PERTAMA. 3. Apabila selama Masa Pemeliharaan telah selesai dan PIHAK KEDUA telah melaksanakan apa yang menjadi kewajibannya selama Masa Pemeliharaan, maka PIHAK KEDUA mengajukan secara tertulis kepada PIHAK PERTAMA untuk dilakukan penyerahan akhir pekerjaan. 4. Sebelum dilakukan penyerahan akhir pekerjaan, atau Direksi Pekerjaan akan melakukan pemeriksaan terhadap hasil pekerjaan yang dilakukan oleh PIHAK KEDUA selama masa pemeliharaan ini. Apabila hasil pemeriksaan pengawas pekerjaan dan/atau Direksi Pekerjaan terhadap hasil pekerjaan PIHAK KEDUA telah sesuai sebagaimana dimaksud pada Perjanjian/Kontrak ini, maka PIHAK PERTAMA akan menerima penyerahan akhir pekerjaan tersebut yang dituangkan dalam Berita Acara Penyerahan Akhir Pekerjaan yang ditandatangani oleh PARA PIHAK dan Direksi Pekerjaan. | C94: -
A95: ='Pemetaan Kontrak '!B31 -> Pembayaran
A96: ='Pemetaan Kontrak '!B32 -> Full | B96: 1. Pembayaran dilakukan oleh PIHAK PERTAMA kepada PIHAK KEDUA dengan mata uang [Mata Uang]. 2. Pembayaran akan dilakukan oleh PIHAK PERTAMA setelah menerima permintaan pembayaran dari PIHAK KEDUA yang dilengkapi dokumen-dokumen: 3.1. Surat Permohonan Pembayaran. 3.2. Berita Acara Pemeriksaan Pekerjaan yang ditandatangani oleh Pengawas Pekerjaan dan PIHAK KEDUA serta diketahui oleh Direksi Pekerjaan. 3.3. Berita Acara Serah Terima Pekerjaan yang ditandatangani oleh Direksi Pekerjaan dan PIHAK KEDUA serta ditandatangani oleh PIHAK PERTAMA. 3.4. Kuitansi 4 (empat) rangkap, bermeterai secukupnya. 3.5. e-faktur pajak. 3.6. Fotokopi Nomor Pokok Wajib Pajak (NPWP). 3.7. Fotokopi Pengukuhan Pengusaha Kena Pajak (PKP). 3.8. Fotokopi Perjanjian. 3. Pembayaran akan dilakukan oleh PIHAK PERTAMA dengan cara transfer ke rekening PIHAK KEDUA sebagaimana berikut: Nama Bank : ______________ No. Rekening : _____________ Atas Nama : << NAMA VENDOR >> | C96: Mata Uang
C97: Nama Bank
C98: No Rekening
C99: Atas Nama
A100: ='Pemetaan Kontrak '!B33 -> Termin | B100: 1. Pembayaran dilakukan dengan tahapan sebagai berikut: 2.1. TAHAP I: pembayaran dilakukan sebesar [Persentase pembayaran termin pertama]% dari Nilai Pekerjaan ditambah PPN sesuai peraturan yang berlaku, setelah PIHAK KEDUA [Kondisi/milestone pembayaran tahap 1] 2.2. TAHAP II: pembayaran dilakukan sebesar [Persentase pembayaran termin kedua]% dari Nilai Pekerjaan ditambah PPN sesuai peraturan yang berlaku, setelah PIHAK KEDUA [Kondisi/milestone pembayaran tahap 2] (Jumlah Tahap menyesuaikan Jumlah Termin) 2. Pembayaran akan dilakukan oleh PIHAK PERTAMA setelah menerima permintaan pembayaran dari PIHAK KEDUA yang dilengkapi dokumen-dokumen: 2.1. Surat Permohonan Pembayaran. 2.2. Berita Acara Pemeriksaan Pekerjaan yang ditandatangani oleh Pengawas Pekerjaan dan PIHAK KEDUA serta diketahui oleh Direksi Pekerjaan. 2.3. Berita Acara Serah Terima Pekerjaan yang ditandatangani oleh Direksi Pekerjaan dan PIHAK KEDUA serta ditandatangani oleh PIHAK PERTAMA. 2.4. Kuitansi 4 (empat) rangkap, bermeterai secukupnya. 2.5. e-faktur pajak. 2.6. Fotokopi Nomor Pokok Wajib Pajak (NPWP). 2.7. Fotokopi Pengukuhan Pengusaha Kena Pajak (PKP). 2.8. Fotokopi Perjanjian/Kontrak. 3. Pembayaran akan dilakukan oleh PIHAK PERTAMA dengan cara transfer ke rekening PIHAK KEDUA sebagaimana berikut: Nama Bank : [Nama Bank] No. Rekening : [No. Rekening] Atas Nama : [Nama Vendor] | C100: Jumlah Termin
C101: Persentase pembayaran termin pertama
C102: Kondisi/milestone pembayaran tahap 1
C103: Persentase pembayaran termin kedua
C104: Kondisi/milestone pembayaran tahap 2
C105: Nama Bank
C106: No. Rekening
C107: Nama Vendor
A108: ='Pemetaan Kontrak '!B34 -> Sanksi dan Denda | B108: 1. Sanksi administrasi yaitu surat peringatan tertulis dapat diberikan oleh PIHAK PERTAMA kepada PIHAK KEDUA dengan ketentuan sebagai berikut: 1.1 Apabila PIHAK KEDUA tidak melaksanakan pekerjaan sesuai dengan persyaratan-persyaratan dan ketentuan-ketentuan sebagaimana yang telah ditetapkan dalam Perjanjian/Kontrak ini, maka PIHAK PERTAMA akan memberikan Surat Peringatan Tertulis I (pertama) kepada PIHAK KEDUA mengenai pekerjaan yang tidak sesuai dengan persyaratan-persyaratan dan ketentuan- ketentuan yang telah ditetapkan tersebut. 1.2 Apabila dalam waktu [jumlah hari batas waktu setelah Surat Peringatan I] Hari Kalender dari Surat Peringatan I (pertama), PIHAK KEDUA belum melaksanakan pekerjaan sebagaimana dimaksud dalam surat peringatan tersebut baik sebagian maupun seluruhnya dan/atau PIHAK KEDUA melakukan kesalahan atau kelalaian kembali maka PIHAK PERTAMA akan memberikan Surat Peringatan II (kedua) kepada PIHAK KEDUA. 1.3 Apabila dalam waktu [jumlah hari batas waktu setelah Surat Peringatan II] Hari Kalender dari Surat Peringatan II (kedua), PIHAK KEDUA belum melaksanakan pekerjaan sebagaimana dimaksud dalam surat peringatan tersebut baik sebagian maupun seluruhnya dan/atau PIHAK KEDUA melakukan kesalahan atau kelalaian Kembali maka PIHAK PERTAMA akan memberikan Surat Peringatan III (ketiga) kepada PIHAK KEDUA, dan PIHAK PERTAMA berhak melakukan klaim terhadap Jaminan Pelaksanaan dan tuntutan kompensasi sebagaimana diatur dalam Perjanjian/Kontrak ini serta mengakhiri Perjanjian/Kontrak secara sepihak. 1.4 PIHAK KEDUA yang menerima Surat Peringatan III (ketiga) dari PIHAK PERTAMA akan dimasukkan ke dalam daftar hitam (blacklist) Perusahaan. 2. Denda dapat dikenakan oleh PIHAK PERTAMA kepada PIHAK KEDUA dengan ketentuan sebagai berikut; 2.1 Apabila PIHAK KEDUA tidak memulai pelaksanaan Pekerjaan dalam waktu 14 (empat belas) hari setelah Tanggal Efektif Perjanjian/Kontrak, maka PIHAK KEDUA akan dikenakan denda sebesar Rp[nominal denda keterlambatan] untuk setiap hari keterlambatan memulai pekerjaan hingga pekerjaan tersebut dimulai oleh PIHAK KEDUA. 2.2 Apabila PIHAK KEDUA dalam melaksanakan pekerjaan melampaui batas waktu yang telah ditentukan sebagaimana diatur pada Perjanjian/Kontrak ini dan, maka PIHAK KEDUA akan dikenakan denda sebesar [minimal 1 ‰ (satu per mil) dari Nilai Perjanjian/Kontrak untuk setiap hari keterlambatan penyelesaian pekerjaan dengan maksimum [sebesar Jaminan Pelaksanaan/5% (lima persen)] dari Nilai Total Perjanjian/Kontrak. 2.3 Apabila PIHAK KEDUA tidak memenuhi besaran TKDN sebagaimana ditentukan dalam Perjanjian/Kontrak ini, maka PIHAK KEDUA akan dikendakan denda sebesar [persentase denda TKDN]% dari Nilai Total Perjanjian/Kontrak. 3. Pelaksanaan sanksi yang tersebut dalam ayat (1) di atas tidak menimbulkan hak bagi PIHAK KEDUA untuk menuntut kompensasi dalam bentuk apapun kepada PIHAK PERTAMA. | C108: Jumlah Hari Batas waktu setelah Surat Peringatan I
C109: Jumlah Hari Batas waktu setelah Surat Peringatan II
...

Sheet KHS Material Ketenagalistrikan
A1: Pasal | C1: Klausul | D1: Data
B2: Header | C2: PT PLN (PERSERO) KONTRAK KESEPAKATAN HARGA SATUAN PENGADAAN [Nama Pengadaan] No: [Nomor Kontrak] Tanggal: [Tanggal Kontrak] PT PLN (PERSERO) DENGAN PT [Nama Penyedia] | D2: Nama pengadaan
D3: Nomor kontrak
D4: Tanggal kontrak
D5: Nama penyedia
B6: KONTRAK | C6: KONTRAK KESEPAKATAN HARGA SATUAN PENGADAAN [MASUKAN NAMA PENGADAAN] Kontrak Kesepakatan Harga Satuan Pengadaan [Nama Pengadaan] berikut semua lampirannya (selanjutnya disebut Kontrak) dibuat dan disepakati di Jakarta pada hari [Hari] tanggal [Tanggal] oleh dan antara: I. PT PLN (PERSERO), suatu perusahaan perseroan yang didirikan berdasarkan hukum Negara Republik Indonesia, berdasarkan Akta Notaris Sutjipto, SH, di Jakarta Nomor 169 tanggal 30 Juli 1994, sebagaimana telah diubah dan terakhir berdasarkan akta Notaris [Notaris] Nomor [No Akta Perubahan Terakhir] tanggal [tanggal akta], dalam hal ini diwakili secara sah oleh [Nama Pengguna] selaku [Jabatan] berdasarkan Keputusan Menteri Badan Usaha Milik Negara selaku RUPS PT PLN (Persero) No. [Nomor SK] tanggal [Tanggal SK] tentang [perihal SK], berkedudukan di [Alamat Unit], selanjutnya disebut Pihak Pertama; dan II. PT [Nama Penyedia], suatu perseroan terbatas yang didirikan berdasarkan hukum Negara Republik Indonesia, berdasarkan Akta Notaris [Nama Notaris] di [Tempat Kewenangan Notaris] Nomor [Nomor Akta] tanggal [Tanggal] sebagaimana telah diubah dan terakhir dengan Akta Notaris [Nama Notaris] di [Tempat Kewenangan Notaris] Nomor [Nomor Akta] tanggal [Masukan Tanggal], dalam hal ini diwakili secara sah oleh [Nama] selaku [Jabatan] berdasarkan [Dasar Kewenangan], berkedudukan di [Domisili], selanjutnya disebut Pihak Kedua. (Selanjutnya Pihak Pertama dan Pihak Kedua secara sendiri-sendiri disebut Pihak dan secara bersama-sama disebut Para Pihak). Para Pihak terlebih dahulu menerangkan hal-hal sebagai berikut: A. Pihak Pertama telah melakukan [Metode Pengadaan] untuk pengadaan [Nama Pengadaan] sesuai Dokumen RKS Nomor [Nomor RKS] tanggal [Masukan Tanggal] secara tepat dan cepat untuk memenuhi kebutuhan operasional Pihak Pertama di seluruh Indonesia. B. Pihak Pertama telah menunjuk Pihak Kedua sebagai salah satu pemenang untuk pengadaan [Nama Pengadaan] tahun [Tahun Pengadaan] melalui surat penunjukan pemenang Nomor [Nomor SPPBJ] tanggal [Tanggal] sebagaimana dilampirkan dalam Lampiran 4 Kontrak ini. C. Pihak Kedua telah memiliki sertifikat Sistem Pengawasan Mutu (SPM) yang berlaku di lingkungan Pihak Pertama / Surat Rekomendasi Mutu (SRM) yang berlaku di lingkungan Pihak Pertama / TPG / Spesifikasi Teknis [disesuaikan terhadap kebutuhan masing-masing pengadaan] sebagaimana terlampir dalam Lampiran 5 Kontrak ini. D. Pihak Kedua telah menandatangani Pakta Integritas sebagaimana terlampir dalam Lampiran 6 Kontrak ini. E. Pihak Kedua menyatakan kepada Pihak Pertama, bahwa Pihak Kedua memiliki keahlian profesional, personil, dan sumber daya teknis, serta telah menyetujui untuk melaksanakan Pekerjaan sesuai dengan persyaratan dan ketentuan dalam Kontrak ini. Berdasarkan hal-hal tersebut di atas, Para Pihak dengan ini sepakat untuk membuat, menandatangani dan melaksanakan Kontrak dengan syarat dan ketentuan sebagai berikut: | D6: Nama pengadaan
D7: Hari
D8: Tanggal
D9: Notaris
D10: No Akta Perubahan Terakhir
D11: tanggal Akta
D12: Nama Pengguna
D13: Jabatan
D14: Nomor SK
D15: Tanggal SK
D16: perihal SK
D17: Alamat Unit
D18: Nama Penyedia
... D32: Jenis Sertifikasi/Spesifikasi Teknis
A33: Pasal 1 | B33: DEFINISI DAN INTERPRETASI | C33: (1) Definisi adalah uraian atau pengertian mengenai istilah-istilah yang digunakan dalam Kontrak. Istilah-istilah tersebut dijelaskan dan diberi arti atau tafsiran sehingga isi Kontrak mudah dipahami oleh setiap orang yang membacanya dan tidak ditafsirkan atau diartikan lain. Dalam Kontrak ini yang dimaksud dengan: (a) Amendemen adalah seluruh perubahan atau penambahan yang diperlukan terhadap Kontrak. (b) Barang adalah suatu material beserta peralatan dan perlengkapannya yang spesifikasinya ditetapkan oleh Pihak Pertama yang mengacu pada Dokumen RKS beserta perubahannya sebagaimana dirinci dalam Lampiran 2 Kontrak ini. (c) Barang Rusak adalah Barang yang cacat produksi atau terdapat ketidaksesuaian baik secara fisik maupun fungsi atau tidak sesuai spesifikasi dan/atau tidak berfungsi sebagian maupun secara keseluruhan (untuk perangkat keras maupun perangkat lunak) baik terpasang maupun belum terpasang sebagaimana disyaratkan dalam Kontrak, sebelum maupun setelah diterima oleh Pengguna Kontrak Rinci, yang disebabkan oleh kesalahan Pihak Kedua. (d) BASTB adalah Berita Acara Serah Terima Barang sebagaimana dirinci lebih lanjut dalam Pasal 15 Kontrak ini dengan format sebagaimana terlampir dalam Lampiran 13 Kontrak ini. (e) Cacat Mutu adalah keadaan hasil Pekerjaan Penyediaan Barang yang tidak berfungsi sesuai dengan persyaratan dalam Kontrak ini. (f) Daftar Penyedia Terseleksi (DPT) adalah daftar Penyedia Barang/Jasa yang dinyatakan lulus oleh Pihak Pertama melalui mekanisme penilaian kualifikasi. (g) Direksi Pekerjaan adalah Senior Manager Perencanaan selaku wakil dari Pengguna Kontrak Rinci pada Unit Induk yang memiliki fungsi pengendalian dan pengawasan Kontrak Rinci serta berwenang untuk menandatangani berita acara sehubungan dengan pelaksanaan Pekerjaan serta melaporkannya secara periodik kepada Wakil Pihak Pertama sebelum dilakukannya Serah Terima Barang. (h) Dokumen Tender atau Rencana Kerja dan Syarat-syarat (Dokumen RKS) adalah dokumen yang disiapkan oleh Pihak Pertama sebagai pedoman dalam proses pembuatan dan penyampaian penawaran oleh Pihak Kedua serta pedoman evaluasi penawaran oleh Pihak Pertama. (i) Estimasi Volume adalah proyeksi volume Barang yang dibutuhkan dalam Tahun Kontrak yang dapat berubah berdasarkan Evaluasi Kinerja sebagaimana dirinci dalam Lampiran 2 Kontrak ini. (j) Evaluasi Kinerja adalah penilaian yang dilakukan oleh Pihak Pertama atas kinerja Pihak Kedua dalam pelaksanaan pekerjaan kontraktual berdasarkan metriks penilaian kinerja kontraktual Penyedia Barang/Jasa yang berlaku di Lingkungan PT PLN (Persero). (k) Harga Satuan adalah harga satuan atas masing-masing Pekerjaan Penyediaan Barang dan Pekerjaan Transportasi sebagaimana dimaksud dalam Pasal 5 Kontrak ini. (l) Jaminan Pelaksanaan adalah jaminan dalam bentuk bank garansi yang diterbitkan oleh pihak-pihak yang dapat menerbitkan jaminan di lingkungan Pihak Pertama yang akan disediakan oleh Pihak Kedua untuk kepentingan Pengguna Kontrak Rinci, dengan tujuan menjamin kewajiban-kewajiban Pihak Kedua berdasarkan Kontrak Rinci. (m) Jangka Waktu Kontrak Rinci adalah jangka waktu berlakunya Kontrak Rinci sebagaimana ditetapkan dalam Kontrak Rinci. (n) Kerugian Langsung adalah kerugian yang diderita oleh Pihak Pertama dan/atau Pengguna Kontrak Rinci karena Barang Rusak atau Cacat Mutu yang mengakibatkan timbulnya peristiwa-peristiwa tertentu yang berdampak langsung kepada Pihak Pertama dan/atau Pengguna Kontrak Rinci, termasuk namun tidak terbatas pada kerusakan atas suatu peralatan, perlengkapan, atau fasilitas Pihak Pertama dan/atau Pengguna Kontrak Rinci. (o) Kontrak Rinci adalah dokumen yang tidak terpisahkan dan menjadi satu kesatuan dengan Kontrak ini. Kontrak Rinci ditandatangani oleh Pengguna Kontrak Rinci untuk mengatur secara rinci mengenai syarat dan ketentuan pelaksanaan Kontrak ini termasuk namun tidak terbatas pada spesifikasi dan ruang lingkup pekerjaan yang akan dilakukan Pihak Kedua, jumlah Barang yang akan dibeli, nilai pembayaran, serta syarat dan ketentuan lainnya yang terkait dengan pelaksanaan Pekerjaan berdasarkan Kontrak ini. (p) Lokasi adalah tempat penerimaan Barang baik pada lokasi PLN Unit Induk atau PLN Unit Pelaksana atau tempat lain yang ditunjuk oleh PLN sebagai destinasi pengiriman Barang sebagaimana dirinci dalam Lampiran 3 Kontrak ini atau sebagaimana ditetapkan lebih lanjut dalam Kontrak Rinci. (q) Pekerjaan adalah Pekerjaan Penyediaan Barang dan Pekerjaan Transportasi. (r) Pekerjaan Penyediaan Barang adalah setiap dan/atau seluruh penyediaan Barang yang meliputi pabrikasi, pengujian, termasuk telah memenuhi SPLN dan pengepakan yang dapat dilakukan secara bertahap termasuk garansi atas Barang yang akan dilaksanakan oleh Pihak Kedua sebagaimana tercantum dalam Lampiran 1 dan Lampiran 2 Kontrak ini. (s) Pekerjaan Transportasi adalah setiap dan/atau seluruh pengiriman atau pengangkutan, bongkar muat, dan asuransi atas Pekerjaan Penyediaan Barang sampai dengan diterimanya Barang oleh Pihak Pertama di Lokasi yang akan dilaksanakan oleh Pihak Kedua, dengan daftar Lokasi pengiriman, biaya transportasi termasuk asuransi sebagaimana dirinci dalam Lampiran 1 dan Lampiran 3 Kontrak ini. (t) Pengguna Kontrak Rinci adalah: 1) [[list] Pengguna] (u) PLN Sub Holding/Anak Perusahaan PLN adalah perusahaan yang sahamnya lebih dari 50% (lima puluh persen) dimiliki oleh PLN. (v) PLN Unit Induk adalah organisasi 1 (satu) tingkat di bawah Kantor Pusat yang dipimpin, dibina, dan dikelola oleh General Manager dan melaksanakan kegiatan usaha penyediaan tenaga listrik tertentu sesuai dengan tujuannya. (w) PLN Unit Pelaksana adalah organisasi 1 (satu) tingkat di bawah Unit Induk atau Pusat-Pusat yang dipimpin, dibina, dan dikelola oleh Manager Unit Pelaksana dan melaksanakan kegiatan ketenagalistrikan tertentu sesuai dengan tujuannya. (x) SCM Marketplace adalah aplikasi yang digunakan untuk pelaksanaan transaksi pembelian Barang/Jasa secara realtime dan akuntabel yang terintegrasi dengan aplikasi PLN, Uji Serah Terima (UST) PLN Pusertif dan tracking pengiriman Barang/Jasa. (y) Sistem Pengawasan Mutu (SPM) adalah sistem pengawasan yang dilakukan oleh PT PLN (Persero) Pusat Sertifikasi terhadap pabrikan dalam negeri yang memproduksi material ketenagalistrikan yang akan digunakan pada instalasi ketenagalistrikan di lingkungan Pihak Pertama dan anak perusahaan Pihak Pertama untuk menjaga mutu produk material/peralatan sesuai dengan standar, dibuktikan dengan terbitnya sertifikat SPM. (z) Standar Perusahaan Listrik Negara (SPLN) adalah standar perusahaan Pihak Pertama yang ditetapkan Direksi Pihak Pertama, bersifat wajib dan dapat berupa peraturan, pedoman, instruksi, cara pengujian dan spesifikasi yang berlaku di lingkungan Pihak Pertama. (aa) Surat Perintah Mulai Kerja (SPMK) adalah surat yang dikeluarkan oleh Pengguna Kontrak Rinci kepada Pihak Kedua yang menyatakan Tanggal Efektif Kontrak Rinci dan untuk memulai pelaksanaan Pekerjaan dengan format sebagaimana Lampiran 8 Kontrak ini, dengan syarat sebagaimana diatur lebih lanjut dalam Kontrak Rinci. (bb) Surat Rekomendasi Mutu (SRM) adalah bukti penilaian awal bahwa suatu pabrikan luar negeri dan agen tunggalnya mempunyai kemampuan dalam memproduksi dan mengedarkan material impor sesuai dengan standar. (cc) Tahun Kontrak adalah tahun sejak tanggal ditandatanganinya Kontrak sampai dengan tahun berakhirnya masa berlaku Kontrak. (dd) Technical Particular and Guarantee (TPG) adalah spesifikasi teknis dan jaminan berdasarkan Dokumen RKS merujuk pada penawaran Pihak Kedua yang telah dievaluasi serta dapat diterima oleh Pihak Pertama. (ee) Tim Pemeriksa Barang adalah petugas-petugas pada PLN Unit Induk atau PLN Unit Pelaksana yang ditunjuk oleh Pengguna Kontrak Rinci termasuk tim yang dibentuk oleh manager unit untuk melaksanakan tugas-tugas sebagaimana diatur dalam Kontrak ini. (ff) Tingkat Komponen Dalam Negeri (TKDN) adalah besaran kandungan dalam negeri pada Barang, jasa, serta gabungan Barang dan jasa, yang dipersyaratkan berdasarkan peraturan perundang-undangan yang berlaku dari waktu ke waktu. (gg) Wakil Pihak Pertama adalah wakil Pihak Pertama yang ditunjuk untuk melakukan pengendalian terhadap pelaksanaan Kontrak ini, sebagaimana di atur pada Pasal 9 Kontrak ini. | D33: [list] Pengguna
A36: Pasal 2 | B36: Hierarki Dokumen | C36: Dalam hal terjadi perbedaan penafsiran atau pertentangan antara ketentuan dalam satu dokumen dengan dokumen lain, maka yang berlaku adalah ketentuan dalam dokumen yang lebih tinggi berdasarkan urutan hierarki sebagai berikut: (a) Kontrak Kesepakatan Harga Satuan beserta perubahannya. (b) Kontrak Rinci beserta perubahannya. (c) Surat Penunjukkan Penyedia Barang/Jasa (SPPBJ). (d) Contract Discussion Agreement (CDA). (e) Addendum/Amendemen Dokumen RKS (apabila ada). (f) Spesifikasi Teknis. (g) Gambar-Gambar (Apabila ada). (h) Daftar kuantitas dan Harga. (i) Instruksi Kepada Penyedia Barang/Jasa. (j) Dokumen lain yang merupakan bagian dari Dokumen Tender/RKS. (k) Surat Penawaran Penyedia Barang/Jasa. | D36: -
A37: Pasal 3 | B37: INTEGRITAS DAN TATA KELOLA PERUSAHAAN YANG BAIK | C37: (1) Sehubungan dengan Kontrak dan hal-hal, dokumen-dokumen, kegiatan-kegiatan, dan transaksi-transaksi yang dimaksud dalam atau terkait dengan Kontrak, Para Pihak menyepakati tidak akan melakukan tindakan-tindakan yang mengakibatkan terjadinya ketidakwajaran dalam pelaksanaan Kontrak termasuk namun tidak terbatas pada tindakan penipuan, penggelapan, pemerasan, kolusi, penyuapan, gratifikasi, korupsi, kecurangan, pemalsuan dan tindakan lain yang tidak sesuai dengan etika bisnis yang baik serta bertentangan dengan peraturan perundang-undangan yang berlaku, termasuk mengenai pemberantasan tindak pidana korupsi, pencegahan dan pemberantasan tindak pidana pencucian uang, penerapan praktik tata kelola perusahaan yang baik (Good Corporate Governance atau GCG) pada Badan Usaha Milik Negara (BUMN), termasuk peraturan yang mengatur mengenai tata kelola anti penyuapan yang berlaku di lingkungan Pihak Pertama. (2) Para Pihak menyepakati bahwa Kontrak dilaksanakan dengan itikad baik, tidak saling mempengaruhi baik langsung maupun tidak langsung guna memenuhi keinginannya, menerima serta bertanggungjawab atas segala keputusan yang ditetapkan sesuai dengan kesepakatan Para Pihak, menghindari serta mencegah terjadinya benturan kepentingan (conflict of interest), menghindari serta mencegah penyalahgunaan wewenang dan/atau kolusi dengan tujuan untuk keuntungan pribadi, golongan atau pihak lain, dan tidak memberi dan/atau menerima, tidak menawarkan atau tidak menjanjikan untuk memberi atau menerima hadiah, imbalan berupa apa saja kepada siapapun yang diketahui atau patut diduga berkaitan dengan pelaksanaan Kontrak. (3) Pihak Kedua menyatakan, menjamin dan berkomitmen kepada Pihak Pertama bahwa dalam melaksanakan Kontrak akan mematuhi ketentuan hukum yang berlaku, termasuk namun tidak terbatas pada peraturan perundang-undangan terkait anti korupsi, anti pencucian uang serta kebijakan Pihak Pertama mengenai anti-fraud dan tata kelola anti-penyuapan seperti: (a) Menerapkan 4 NO (TIDAK), yaitu: (i) No bribery, menghindari suap menyuap dan pemerasan; (ii) No gift, menghindari hadiah atau gratifikasi yang bertentangan dengan peraturan yang berlaku; (iii) No kickback, menghindari komisi, tanda terima kasih baik dalam bentuk uang atau bentuk lainnya; dan (iv) No luxurious hospitality, menghindari jamuan yang berlebihan. (b) Mengikuti prosedur uji kelayakan berbasis integritas (Integrity Due Diligence) yang diterapkan Pihak Pertama. (c) Mengikuti program sosialisasi Sistem Manajemen Anti-Penyuapan yang dilaksanakan Pihak Pertama yang dapat diwakili oleh karyawan perusahaan Pihak Kedua yang ditunjuk untuk mewakili Pihak Kedua. (d) Menandatangani dan melaksanakan Pakta Integritas Pihak Kedua. (e) Melaporkan insiden fraud melalui Whistle Blowing System Pihak Pertama. (4) Pihak Pertama akan melakukan audit terkait tagihan pembayaran dan dokumen pembukuan serta pencatatan Pihak Kedua ketika terdapat indikasi ketidakwajaran berupa overcharge atau overprice dari tagihan yang disampaikan oleh Pihak Kedua kepada Pihak Pertama, dimana tujuan pelaksanaan audit tersebut untuk memastikan kesesuaian tagihan Pihak Kedua dengan ketentuan yang berlaku termasuk kesesuaian dengan ketentuan dalam Kontrak. (5) Pelaksanaan audit sebagaimana dimaksud dalam ayat (4) Pasal ini, dilakukan dengan ketentuan sebagai berikut: (a) atas biaya Pihak Pertama; (b) dilakukan dengan pemberitahuan oleh Pihak Pertama kepada Pihak Kedua selambat-lambatnya 7 (tujuh) hari kalender sebelum pelaksanaan audit; (c) pelaksanaan audit dilaksanakan paling lambat dalam waktu 7 (tujuh) hari kerja, dilanjutkan dengan pembuatan pelaporan audit oleh Pihak Pertama paling lambat dalam 3 (tiga) hari kerja; (d) penyelesaian pembayaran (settlement/adjustment) dilakukan paling lambat dalam 30 (tiga puluh) hari kalender setelah Pihak Pertama memaparkan laporan hasil audit kepada Pihak Kedua; (e) Pihak Pertama dapat menunjuk pihak lain untuk melakukan audit; (f) Pihak Kedua wajib mengizinkan perwakilan Pihak Pertama dan menyediakan dokumen dan data yang diperlukan; (g) permintaan dan penyampaian dokumen dan data audit dilaksanakan pada jam kerja Pihak Kedua; (h) apabila terdapat kerjasama antara Pihak Kedua dengan pihak ketiga yang berkaitan dengan pelaksanaan Kontrak, maka Pihak Kedua wajib memastikan dan menuangkan ketentuan mengenai hak akses Pihak Pertama terhadap dokumen dan data milik pihak ketiga dalam perjanjian antara Pihak Kedua dengan pihak ketiga tersebut; dan (i) Para Pihak termasuk perwakilannya, akan menjaga kerahasiaan informasi non-publik yang diperoleh dari pelaksanaan audit tersebut. (6) Dalam pelaksanaan audit terhadap tagihan pembayaran sebagaimana dimaksud ayat (4) Pasal ini, Pihak Pertama berhak melakukan penundaan pembayaran atas tagihan pembayaran tersebut atau dapat melakukan pembayaran melalui suatu rekening khusus (escrow account) yang dibuat oleh Para Pihak yang beban biayanya menjadi tanggung jawab Pihak Kedua sampai dilakukan penyesuaian pembayaran. (7) Dalam hal dilakukan audit sebagaimana dimaksud ayat (4) Pasal ini dan/atau pelaksanaan penundaan pembayaran sebagaimana dimaksud ayat (6) Pasal ini, maka Pihak Kedua wajib untuk tetap melaksanakan kewajibannya sesuai Kontrak ini. (8) Dalam rangka penerapan tata kelola yang baik (Good Corporate Governance) di lingkungan Pihak Pertama, apabila dalam proses pelaksanaan Kontrak ini Pihak Kedua mengetahui adanya tindakan kecurangan, pelanggaran peraturan atau hukum, konflik kepentingan, penyuapan atau gratifikasi, maupun kelakuan tidak etis yang dilakukan oleh pegawai Pihak Pertama, maka Pihak Kedua agar melaporkannya melalui Whistle Blower System dengan menggunakan media antara lain yaitu: (a) Website : https://cos.pln.co.id; (b) Telepon atau Pesan Singkat (SMS) atau Whatsapp ke nomor: 08119861901; atau (c) Email ke: wbpln@pln.co.id; atau (d) Surat kepada Executive Vice President Kepatuhan PT PLN (Persero) Kantor Pusat Jalan Trunojoyo Blok M – I No. 135 Kebayoran Baru, Jakarta 12160. (9) Pihak Kedua yang menurut penilaian Pihak Pertama sehubungan dengan pelaksanaan Kontrak terbukti melakukan larangan-larangan sebagaimana dimaksud pada Pasal ini dapat dikenakan sanksi oleh Pihak Pertama, yaitu sebagai berikut: (a) Pemutusan Kontrak secara sepihak; (b) dalam hal terjadi pemutusan Kontrak, maka Jaminan Pelaksanaan akan dicairkan dan disetorkan ke rekening Pihak Pertama; dan (c) Pihak Kedua dikenakan sanksi daftar hitam (blacklist) sesuai ketentuan yang berlaku di Pihak Pertama. | D37: -
A40: Pasal 4 | B40: LINGKUP PEKERJAAN | C40: (1) Pihak Kedua setuju untuk melaksanakan, menyelesaikan dan melengkapi setiap dan seluruh Pekerjaan dalam semua aspek dan sesuai dengan ketentuan-ketentuan dalam Kontrak ini, dengan lingkup pekerjaan sebagai berikut: (a) Pekerjaan Penyediaan Barang; dan (b) Pekerjaan Transportasi. (2) Pekerjaan Penyediaan Barang merujuk pada: (a) Rincian spesifikasi dan Harga Satuan atas Pekerjaan Penyediaan Barang sebagaimana ditetapkan dalam Lampiran 1 Kontrak ini; dan (b) besaran Estimasi Volume atas Barang serta komitmen kesanggupan kapasitas produksi Barang sebagaimana ditetapkan dalam Lampiran 2 Kontrak ini. (3) Pekerjaan Transportasi merujuk pada rincian Lokasi pengiriman dengan biaya transportasi berikut asuransi sebagaimana ditetapkan dalam Lampiran 1 dan Lampiran 3 Kontrak ini. | D40: -
A41: Pasal 5 | B41: HARGA SATUAN | C41: (1) Harga Satuan adalah sebagaimana ditetapkan dalam Lampiran 1 Kontrak ini berlaku dan mengikat Para Pihak untuk jangka waktu 1 (satu) tahun atau sepanjang Jangka Waktu Penerbitan. | D41: -
A42: Pasal 6 | B42: ESTIMASI VOLUME BARANG | C42: (1) Estimasi Volume sebagaimana dirinci pada Lampiran 2 Kontrak ini adalah merupakan acuan awal dan bukan merupakan komitmen pemesanan dan pembelian Barang dan pelaksanaan Pekerjaan. (2) Komitmen pemesanan dan pembelian Barang serta pelaksanaan Pekerjaan Penyediaan Barang dan Pekerjaan Transportasi secara rinci dan aktual yang akan dipasok oleh Pihak Kedua kepada Pihak Pertama adalah merujuk pada besaran volume dan jadwal pengiriman yang ditetapkan dalam masing-masing Kontrak Rinci. (3) Sebagai bagian dari Pekerjaan Penyediaan Barang, Pihak Kedua wajib untuk memastikan dan menyediakan Barang sebesar Estimasi Volume dan sesuai dengan komitmen kesanggupan kapasitas produksi Barang sebagaimana tercantum pada Lampiran 2 Kontrak ini. | D42: -
A43: Pasal 7 | B43: JANGKA WAKTU BERLAKUNYA KONTRAK | C43: (1) Kontrak ini akan berlaku efektif dan mengikat sejak ditandatangani oleh Para Pihak dan akan terus menerus berlaku sampai dengan seluruh hak dan kewajiban yang timbul dari seluruh Kontrak Rinci terpenuhi. (2) Kontrak Rinci dapat diterbitkan setelah Kontrak ini berlaku efektif sampai dengan tanggal [Tanggal] (Jangka Waktu Penerbitan), kecuali Kontrak ini disepakati untuk diakhiri lebih awal sebagaimana dimaksud dalam Pasal 31 Kontrak ini atau terjadi pemutusan Kontrak sebagaimana dimaksud dalam Pasal 31 Kontrak ini. (3) Apabila Jangka Waktu Penerbitan sebagaimana diatur dalam ayat (2) Pasal ini telah terlampaui, maka Pengguna Kontrak Rinci tidak dapat menerbitkan Kontrak Rinci. Jangka Waktu Penerbitan ini dapat diperpanjang oleh Para Pihak berdasarkan kesepakatan bersama sebelum berakhirnya Jangka Waktu Penerbitan dengan tanpa adanya penambahan volume. Perubahan Jangka Waktu Penerbitan ini selanjutnya dituangkan dalam suatu Amendemen. (4) Masa berlaku Kontrak Rinci dapat melampaui Jangka Waktu Penerbitan dan segala kewajiban Para Pihak tetap berlaku sesuai dengan syarat dan ketentuan yang diatur dalam Kontrak ini dan Kontrak Rinci. | D43: Tanggal berakhirnya Kontrak Rinci
A44: Pasal 8 | B44: PENERBITAN KONTRAK RINCI DAN PELAKSANAAN PEKERJAAN | C44: (1) Setelah ditandatanganinya Kontrak ini, Pihak Kedua akan menandatangani suatu Kontrak Rinci dengan masing-masing Pengguna Kontrak Rinci sesuai dengan format dalam Lampiran 7 Kontrak ini yang merupakan satu kesatuan yang tidak terpisahkan dari Kontrak ini. (2) Pembuatan dan penandatanganan Kontrak Rinci termasuk pemberian Pekerjaan dilakukan berdasarkan pada kebutuhan dan ketersediaan anggaran pada masing-masing PLN Unit Induk/PLN Unit Pelaksana terkait dengan tetap merujuk pada komitmen kesanggupan kapasitas produksi Barang dalam Lampiran 2 Kontrak ini. (3) Sejak tanggal efektif Kontrak Rinci yang ditandai dengan terbitnya SPMK (Tanggal Efektif Kontrak Rinci), Pihak Kedua akan melaksanakan dan menyelesaikan tiap-tiap Pekerjaan sesuai dengan jadwal dan jangka waktu sebagaimana dirinci pada Lampiran 3 Kontrak ini atau Kontrak Rinci (Jangka Waktu Pelaksanaan Pekerjaan). (4) Pelaksanaan Pekerjaan pada Kontrak Rinci tetap mengacu pada Jangka Waktu Pelaksanaan Pekerjaan sebagaimana diatur pada Lampiran 3 Kontrak ini yang akan ditentukan lebih lengkap dalam Kontrak Rinci bersangkutan. (5) Konsekuensi dan risiko atas terjadinya keterlambatan pelaksanaan Pekerjaan sebagaimana diatur dalam Kontrak Rinci maka diberlakukan sesuai ketentuan dalam Kontrak ini. | D44: -
A45: Pasal 9 | B45: PENGENDALIAN DAN PENGAWASAN | C45: (1) Pihak Pertama menunjuk [Satuan Kerja Pengendalian Kontrak] sebagai wakil Pihak Pertama untuk melakukan pengendalian terhadap pelaksanaan Kontrak ini. (2) Untuk kelancaran pelaksanaan Pekerjaan, Pengguna Kontrak Rinci yang relevan berwenang untuk membuat Kontrak Rinci dan dibantu oleh Direksi Pekerjaan untuk bertanggung jawab untuk melakukan pengendalian dan pengawasan terhadap pelaksanaan Pekerjaan, serta memberikan bimbingan dan petunjuk yang diperlukan demi kelancaran pelaksanaan Pekerjaan. (3) Pengguna Kontrak Rinci dapat memberikan peringatan tertulis kepada Pihak Kedua dalam hal terdapat ketidaksesuaian pelaksanaan Kontrak Rinci sebagaimana Pasal 27 berdasarkan laporan dan justifikasi dari Manager Unit Pelaksana. (4) Pengguna Kontrak Rinci dalam melaksanakan tugasnya sebagaimana dimaksud pada ayat (2) Pasal ini dapat menunjuk Tim Pemeriksa Barang. (5) Pihak Pertama atau wakil Pihak Pertama memiliki kewenangan untuk melakukan hal-hal sebagai berikut: (a) melaksanakan koordinasi, monitoring dan pengaturan kuota dan/atau alokasi Barang; (b) melakukan pemeriksaan dan verifikasi atas hasil Evaluasi Kinerja Pihak Kedua yang dilakukan oleh masing-masing Pengguna Kontrak Rinci; (c) memberikan peringatan tertulis kepada Pihak Kedua dalam hal Pihak Kedua tidak dapat melaksanakan sebagian atau seluruh kewajibannya sebagaimana disebutkan dalam Kontrak ini; (d) memberikan peringatan tertulis kepada Pihak Kedua berdasarkan hasil Evaluasi Kinerja Pihak Kedua atas pelaksanaan Pekerjaan; (e) mendorong Peningkatan Penggunaan Produksi Dalam Negeri (P3DN) melalui pelaksanaan audit TKDN dengan melakukan verifikasi data antara lain namun tidak terbatas pada bill of material, purchase order komponen material, dokumen impor, dan dokumen lain yang berhubungan dengan produksi Barang. (6) Pihak Pertama memiliki kewenangan untuk menunjuk PT PLN (Persero) Pusat Sertifikasi atau pihak lainnya guna melakukan monitoring proses produksi dan audit kesiapan produksi yang meliputi jadwal produksi, kesiapan sarana dan pengujian, kesiapan SDM, serta kesiapan bahan baku yang akan dilakukan segera setelah Kontrak ditandatangani dengan merujuk pada jadwal yang ditetapkan Pihak Pertama. Monitoring proses produksi dan audit kesiapan produksi dapat dilakukan secara berkala sesuai kebutuhan Pihak Pertama. Setiap hasil monitoring proses produksi dan audit kesiapan produksi akan dilaporkan oleh pihak yang ditunjuk Pihak Pertama. (7) Pihak Pertama memiliki kewenangan untuk melakukan pengawasan, pengujian atau audit Pekerjaan yang sudah dan sedang dilaksanakan oleh Pihak Kedua, termasuk namun tidak terbatas pada penyediaan material kualitas tinggi sesuai spesifikasi yang dipersyaratkan, komponen material yang digunakan berasal dari penyedia komponen yang berkualitas, dan sistem kontrol kualitas internal sesuai dengan SPLN atau standar lainnya yang berlaku. Biaya pengawasan, pengujian atau audit menjadi beban Pihak Pertama. (8) Pihak Kedua wajib menyediakan akses kepada Pihak Pertama dalam melakukan monitoring proses produksi dan audit kesiapan produksi, pengawasan, pengujian, dan/atau audit Pekerjaan. Pihak Kedua wajib memberikan dokumentasi yang dibutuhkan dan klarifikasi selama proses tersebut berlangsung untuk menjamin kualitas Barang sesuai spesifikasi yang dipersyaratkan dalam Kontrak. | D45: Satuan Kerja Pengendalian Kontrak
A47: Pasal 10 | B47: UJI SERAH TERIMA | C47: (1) Pihak Kedua wajib menyediakan Barang yang dibutuhkan oleh Pihak Pertama agar dapat dilakukan uji serah terima. (2) Ketentuan uji serah terima merupakan bagian yang tidak terpisahkan dari proses sistem pengawasan mutu serta perjanjian sistem pengawasan mutu antara Pihak Kedua dengan PT PLN (Persero) Pusat Sertifikasi atau pihak yang ditunjuk oleh Pihak Pertama. Apabila diperlukan, Pihak Pertama dan/atau Wakil Pihak Pertama dan Pihak Kedua dapat menyaksikan pengujian tersebut. (3) Mengacu pada pelaksanaan uji serah terima Barang sebagaimana dimaksud pada ayat (2) Pasal ini, maka akan diterbitkan suatu laporan hasil uji serah terima Barang (Laporan Hasil Uji Serah Terima Barang). (4) Pengujian serah terima Barang mengacu kepada SPLN yang disyaratkan atas Barang dan/atau standar lain yang berlaku. Apabila diperlukan, Pihak Pertama akan melakukan pengujian tambahan termasuk memberikan tambahan mata uji yang dibutuhkan. Seluruh biaya pengujian tambahan Barang menjadi tanggung jawab Pihak Pertama. (5) Apabila Laporan Hasil Uji Serah Terima Barang sebagaimana dimaksud pada ayat (3) Pasal ini gagal, maka Pihak Pertama dapat memberlakukan ketentuan tentang pengawasan mutu yang ditetapkan dalam lingkungan Pihak Pertama termasuk namun tidak terbatas pada Sistem Pengawasan Mutu (SPM) material ketenagalistrikan dan/atau ketentuan lain yang berlaku. (6) Setiap dan seluruh Barang yang diindikasikan gagal sesuai hasil pemeriksaan uji serah terima Barang wajib diganti oleh Pihak Kedua hingga memenuhi spesifikasi sesuai yang diatur dalam Kontrak. (7) Dalam hal terjadi perubahan spesifikasi Barang sehubungan dengan kebutuhan Pihak Pertama atau berdasarkan SPLN yang disyaratkan atas Barang atau standar lain yang berlaku, Pihak Kedua wajib memenuhi perubahan tersebut dan menyerahkan Barang sesuai dengan spesifikasi yang baru yang ditentukan Pihak Pertama. Mekanisme perubahan akan disepakati lebih lanjut oleh Para Pihak. (8) Dalam hal terjadi perubahan komponen Barang karena security of supply dan peningkatan kualitas Barang yang telah lulus uji verifikasi oleh PT PLN (Persero) Pusat Sertifikasi atau pihak yang ditunjuk oleh Pihak Pertama, maka Pihak Kedua dapat mengajukan usulan perubahan tersebut kepada Pihak Pertama dan perubahan hanya dapat dilakukan berdasarkan persetujuan Pihak Pertama. (9) Pihak Kedua hanya akan dan wajib mengirimkan Barang setelah materi uji serah terima Barang dinyatakan lulus dalam Laporan Hasil Uji Serah Terima Barang yang dikeluarkan oleh pihak yang ditunjuk Pihak Pertama. (10) Pihak Kedua dapat mengirimkan Barang yang telah dinyatakan lulus dalam Laporan Hasil Uji Serah Terima Barang yang dilakukan sebelum Kontrak ini ditandatangani, setelah mendapatkan verifikasi tertulis berupa covering letter dari PT PLN (Persero) Pusat Sertifikasi atau pihak yang ditunjuk oleh Pihak Pertama. (11) Apabila terjadi proses investigasi atas kerusakan Barang yang telah terpasang, maka PT PLN (Persero) Pusat Sertifikasi atau pihak yang ditunjuk oleh Pihak Pertama dapat menaikkan jumlah sample Barang yang akan diuji serah terimakan. (12) Pada kondisi khusus dan atas permintaan tertulis dari Pihak Pertama, uji serah terima dan pengiriman Barang akan diatur dengan mekanisme tersendiri. | D47: -
A49: Pasal 11 | B49: PEKERJAAN PENYEDIAAN BARANG | C49: (1) Sejak Tanggal Efektif Kontrak Rinci, Pihak Kedua akan melaksanakan Pekerjaan Penyediaan Barang sesuai dengan jadwal dan jangka waktu sebagaimana dirinci pada Lampiran 3 Kontrak ini. (2) Pihak Kedua berkewajiban atas tanggungannya sendiri untuk mengepak Barang sedemikian rupa sehingga Barang terhindar dan terlindungi dari risiko kerusakan atau kehilangan selama masa transportasi atau pada saat pengiriman dari tempat asal Barang sampai ke Lokasi. (3) Pengepakan, penandaan dan penyertaan dokumen di dalam dan di luar paket Barang harus dilakukan dengan mencantumkan keterangan sebagai berikut: (a) Nama Barang; (b) Nomor Serial; (c) Merek; (d) Tipe/Jenis; (e) Rating; (f) Kontrak No./Tanggal; (g) Kontrak Rinci No./Tanggal; (h) Alamat Tujuan; dan (i) Jumlah Barang. Dapat disesuaikan terhadap kebutuhan masing-masing pengadaan | D49: -
A50: Pasal 12 | B50: PEKERJAAN TRANSPORTASI | C50: (1) Setelah penyelesaian Pekerjaan Penyediaan Barang, Pihak Kedua berkewajiban melakukan Pekerjaan Transportasi berupa pengiriman Barang ke Lokasi. (2) Dalam melakukan Pekerjaan Transportasi, Pihak Kedua berkewajiban memberitahukan terlebih dahulu secara tertulis selambat-lambatnya 7 (tujuh) hari kerja sebelum pengiriman Barang kepada Pengguna Kontrak Rinci untuk setiap pengiriman Barang ke Lokasi. (3) Pihak Kedua wajib membuat surat jalan sebanyak minimal 2 (dua) rangkap yang berisi rincian pengiriman Barang dan dokumen terkait lainnya yang harus diserahkan oleh Pihak Kedua dan akan ditandatangani oleh petugas dari Pengguna Kontrak Rinci pada saat Barang sampai di Lokasi. (4) Pihak Kedua harus mempersiapkan Barang termasuk semua perlengkapannya yang akan dikirimkan ke Lokasi dengan cara transportasi tertentu termasuk kelengkapan peralatan transportasi dan melindunginya dari segala kerusakan atau kerugian serta bertanggung jawab untuk memperbaiki dan/atau mengganti segala kerusakan dan/atau kehilangan Barang termasuk peralatan atas Barang tersebut. (5) Pihak Kedua berkewajiban untuk tunduk dan menaati segala Peraturan perundang-undangan yang berlaku di Negara Kesatuan Republik Indonesia tentang pengiriman dan pendistribusian barang/jasa. (6) Pihak Kedua harus bertanggung jawab untuk mendapatkan perizinan dari pemerintah baik pusat maupun daerah dan/atau instansi lain sehubungan dengan pengurusan transportasi dan pemindahan Barang termasuk perlengkapan atas Barang tersebut. (7) Pihak Kedua harus mentransportasikan semua Barang maupun perlengkapan atas Barang yang tercantum dalam Kontrak ini ke Lokasi dan tetap bertanggung jawab penuh atas pemuatan, pembongkaran, penanganan, pengangkutan, penyimpanan di lapangan dan asuransi yang diperlukan (Transportation Insurance). (8) Semua biaya transportasi atas Pekerjaan Transportasi (termasuk pemuatan dan penyimpanan) adalah sebagaimana tercantum dalam Lampiran 1 Kontrak ini. (9) Pihak Kedua wajib mengasuransikan setiap Barang yang akan diserahkan dan pengiriman Barang sesuai dengan ketentuan peraturan perundang-undangan yang berlaku. Seluruh biaya-biaya yang timbul atas pelaksanaan Pasal ini menjadi beban dan tanggung jawab Pihak Kedua. (10) Apabila Pihak Kedua tidak melakukan pemberitahuan sebagaimana dimaksud pada ayat (2) Pasal ini, sehingga Barang tidak dapat ditempatkan di Lokasi yang bersangkutan, maka segala risiko dan biaya yang timbul menjadi beban dan tanggung jawab Pihak Kedua. (11) Konsekuensi dan risiko terhadap kerusakan dan/atau kehilangan Barang yang terjadi sebelum Barang diserahterimakan oleh Pihak Kedua kepada Pengguna Kontrak Rinci di Lokasi yang dinyatakan dalam setiap BASTB merupakan beban dan tanggung jawab Pihak Kedua. (12) Pihak Pertama memiliki hak setiap saat untuk melakukan transportasi Barang sesuai dengan mekanisme pengiriman Barang atau pengaturan logistik Pihak Pertama. Dalam hal Pihak Pertama melakukan maksudnya tersebut, maka Para Pihak sepakat bahwa Pihak Pertama tidak berkewajiban untuk melakukan pembayaran atas biaya transportasi dan asuransi atas Barang terkait. | D50: -
... A78: Pasal 34 | B78: ADMINISTRASI DAN SURAT MENYURAT | C78: (1) Setiap pemberitahuan yang berkaitan dengan Kontrak ini harus dilaksanakan secara tertulis dalam bentuk surat dan/atau email. Pemberitahuan secara lisan dan/atau telepon harus dikuatkan dengan pemberitahuan secara tertulis dalam bentuk surat dan/atau email dalam waktu 24 (dua puluh empat) jam sejak pemberitahuan lisan atau telepon tersebut disampaikan. (2) Setiap pemberitahuan untuk masing-masing Pihak ditujukan kepada pejabat dengan alamat sebagai berikut : PT PLN (PERSERO) [Nama Unit] Alamat : [Alamat Unit] Facsimile/Telepon : [Nomor Facsimile/Telepon] Untuk perhatian : [Nama Jabatan UP] PT [Masukan Nama Penyedia] Alamat : [Alamat] Facsimile/Telepon : [Nomor Telepon] Untuk perhatian : [Pihak Yang Dituju] Email : [Alamat Email] (3) Apabila terjadi perubahan alamat Para Pihak sebagaimana tercantum pada ayat (2) Pasal ini, maka Para Pihak harus memberitahukan perubahan alamat secara tertulis kepada Pihak lainnya. | D78: Nama Unit
D79: Alamat Unit
D80: Nomor Facsimile/Telepon
D81: Nama Jabatan UP
D82: Nama penyedia Barang/Jasa
D83: Alamat penyedia Barang/Jasa
D84: Nomor Telepon penyedia Barang/Jasa
D85: Pihak yang dituju
D86: Alamat email penyedia Barang/Jasa
A87: Pasal 35 | B87: PENGGUNAAN DOKUMEN KONTRAK DAN KERAHASIAAN | C87: (1) Para Pihak harus: (a) merahasiakan ketentuan-ketentuan Kontrak ini serta semua informasi rahasia yang dimilikinya berkaitan dengan Pihak lain sebagai akibat dari menegosiasikan atau membuat Kontrak ini (Informasi Rahasia); (b) menggunakan Informasi Rahasia tersebut semata-mata dan secara eksklusif untuk tujuan dan keuntungan usaha atau untuk mengambil keputusan-keputusan mengenai pelaksanaan Kontrak; dan (c) mengambil atau menyebabkan diambil segala tindakan pengamanan yang diperlukan untuk menjaga kerahasiaan Informasi Rahasia. (2) Para Pihak dapat mengungkapkan, atau mengizinkan pengungkapan, informasi yang dengan cara lain bersifat rahasia jika dan sampai batas (i) diwajibkan oleh hukum atau instansi pemerintah, dalam hal mana, ia harus mendapat persetujuan tertulis sebelumnya dari Pihak lainnya sehubungan dengan syarat-syarat pengungkapan tersebut, (ii) diungkapkan kepada masing-masing afiliasinya, pemegang sahamnya, dan penasihat profesionalnya atau pejabatnya (tetapi ia harus tetap bertanggung jawab atas kepatuhan terhadap Pasal ini), atau (iii) menjadi domain publik selain akibat dari pelanggaran oleh satu Pihak pada Kontrak ini. (3) Pemberitahuan, siaran pers atau komunikasi lain apapun jenisnya yang terkait dengan negosiasi Para Pihak atau pokok masalah atau syarat-syarat Kontrak ini tidak dapat dapat dibuat atau diijinkan oleh, atau dibuat atas nama Pihak manapun, tanpa persetujuan tertulis sebelumnya dari Pihak lainnya kecuali dimana pengumuman, siaran pers, atau komunikasi tersebut harus dibuat berdasarkan Undang-Undang atau perintah instansi pemerintah, dalam hal mana, ia akan berkonsultasi dengan Pihak lainnya sehubungan dengan ketentuan-ketentuan pengungkapan tersebut dan mendapatkan persetujuan Pihak lainnya (persetujuan mana tidak boleh ditahan-tahan, ditunda, atau bersyarat secara tidak wajar). | D87: -
A88: Pasal 36 | B88: HAK ATAS KEKAYAAN INTELEKTUAL | C88: (1) Pihak Kedua menjamin bahwa semua Barang dan/atau jasa yang digunakan untuk Pekerjaan ini tidak melanggar Hak atas Kekayaan Intelektual (HAKI) pihak manapun dan dalam bentuk apapun. (2) Pihak Kedua wajib melindungi Pihak Pertama dan/atau Pengguna Kontrak Rinci dari segala tuntutan atau klaim dari pihak ketiga atas pelanggaran HAKI. | D88: -
A89: Pasal 37 | B89: AMENDEMEN | C89: (1) Setiap perubahan atas Kontrak dituangkan dalam Amendemen Kontrak yang merupakan bagian yang tidak terpisahkan dari Kontrak dan dibuat atas kesepakatan bersama antara Para Pihak. (2) Perubahan Kontrak dapat dilakukan meliputi: (a) Mengubah spesifikasi teknis Pekerjaan; (b) Adanya perubahan ketentuan/peraturan yang berlaku; atau (c) Hal-hal lain yang dianggap perlu dan sesuai kebutuhan Pihak Pertama. (3) Perubahan terhadap Kontrak Rinci dapat dilakukan dengan kesepakatan tertulis yang dituangkan dalam bentuk Amendemen yang ditandatangani oleh Pengguna Kontrak Rinci dan Pihak Kedua dengan tetap tunduk pada ketentuan dalam Kontrak dan merupakan bagian yang tidak terpisahkan dengan Kontrak ini. | D89: -
A90: Pasal 38 | B90: BAHASA DAN HUKUM | C90: Kontrak ini dibuat dan ditafsirkan berdasarkan bahasa Indonesia serta tunduk berdasarkan hukum yang berlaku di Negara Kesatuan Republik Indonesia. | D90: -
A91: Pasal 39 | B91: PAJAK DAN PERIZINAN | C91: (1) Pihak Kedua harus mengetahui, memahami dan patuh terhadap semua peraturan perundang-undangan tentang pajak yang berlaku di Indonesia dan sudah memperhitungkannya dalam pelaksanaan Kontrak ini. (2) Pajak-pajak yang berhubungan dengan pelaksanaan Kontrak menjadi tanggung jawab masing-masing Pihak berdasarkan peraturan dan perundang-undangan terkait perpajakan yang berlaku. (3) Pihak Kedua wajib memperoleh seluruh persetujuan dan izin yang diperlukan sehubungan dengan pelaksanaan Pekerjaan termasuk namun tidak terbatas pada perizinan umum, perizinan khusus/operasional, perizinan dari pemerintah setempat maupun dispensasi yang diperlukan untuk pelaksanaan Pekerjaan. (4) Semua biaya perizinan, pungutan lainnya yang diperlukan untuk pelaksanaan Pekerjaan dan retribusi yang berlaku sesuai dengan peraturan daerah menjadi tanggung jawab Pihak Kedua. | D91: -
A92: Pasal 40 | B92: PENGALIHAN | C92: (1) Hak dan kewajiban yang timbul berdasarkan Kontrak ini tidak dapat dialihkan oleh salah satu Pihak kepada siapapun tanpa persetujuan tertulis dari Pihak lainnya. (2) Apabila terdapat persetujuan tertulis dari masing-masing Pihak, setiap Pihak yang menerima pengalihan tersebut wajib untuk menyetujui secara tertulis untuk mengikatkan diri pada ketentuan dalam Kontrak ini secara keseluruhan tanpa pengecualian. | D92: -
A93: Pasal 41 | B93: PELEPASAN HAK | C93: Masing-masing Pihak dianggap tidak melepaskan suatu hak berdasarkan Kontrak ini, kecuali jika Pihak tersebut telah menyampaikan kepada Pihak lain suatu pelepasan hak secara tertulis yang ditandatangani oleh Pihak yang melepaskan hak itu. Penundaan atau kelalaian dalam pelaksanaan suatu hak atau hak untuk menuntut perbaikan tidak dianggap sebagai suatu pelepasan hak atas suatu kelalaian atau suatu persetujuan (diam-diam) atas kelalaian tersebut. | D93: -
A94: Pasal 42 | B94: PENGESAMPINGAN | C94: (1) Setiap pengesampingan terhadap ketentuan Kontrak ini harus dalam bentuk tertulis dan ditandatangani oleh Pihak atau Para Pihak yang memberikan pengesampingan tersebut. (2) Kedua belah Pihak tidak akan dianggap telah mengesampingkan hak apapun berdasarkan Kontrak ini, kecuali Pihak tersebut telah mengirimkan kepada Pihak lainnya pengesampingan tertulis yang ditandatangani oleh pejabat yang berwenang dari Pihak yang mengesampingkan haknya tersebut. Keterlambatan atau tidak dilakukannya suatu kewenangan atau perbaikan tidak akan dianggap sebagai pengesampingan atas setiap kelalaian atau persetujuan (diam-diam) di dalam Kontrak ini. | D94: -
A95: Pasal 43 | B95: KETERPISAHAN | C95: (1) Apabila salah satu ketentuan dalam Kontrak ini diputuskan oleh pengadilan menjadi tidak sah, tidak berlaku dan tidak dapat dilaksanakan dengan alasan apapun, ketentuan tersebut tidak akan mempengaruhi keabsahan dan dapat dilaksanakannya ketentuan-ketentuan lain dalam Kontrak ini. Para Pihak sepakat bahwa bagian lain dari Kontrak ini akan tetap berlaku, mengikat dan dapat dilaksanakan oleh Para Pihak sepanjang hal tersebut diperbolehkan sesuai dengan Hukum Indonesia. (2) Para Pihak akan melakukan upaya terbaik untuk menggantikan ketentuan yang dinyatakan tidak sah, tidak berlaku dan tidak dapat dilaksanakan dengan ketentuan yang sama atau mirip dalam tujuan dan isi ketentuan tersebut yang dapat dilaksanakan secara sah. (3) Para Pihak setuju bahwa dalam hal terdapat ketentuan yang tidak sah atau tidak dapat diberlakukan sebagaimana dimaksud di atas, maka ketentuan tersebut akan diganti dengan ketentuan yang sah menurut hukum dan sedapat mungkin mencerminkan maksud dan tujuan komersial dibuatnya ketentuan tersebut. | D95: -
A96: Pasal 44 | B96: PENGELUARAN-PENGELUARAN | C96: Masing–masing Pihak akan menanggung biaya dan pengeluaran sendiri (termasuk, namun tidak terbatas pada biaya dan pengeluaran agen, perwakilan, penasihat, pengacara dan akuntan) yang diperlukan untuk negosiasi, persiapan, pelaksanaan, penyerahan, dan pemenuhan Kontrak ini. | D96: -
A97: Pasal 45 | B97: LAIN-LAIN | C97: (1) Kontrak ini (berikut lampiran-lampirannya), dokumen dan kelengkapan yang harus ditandatangani atau diserahkan merupakan suatu perjanjian final, lengkap dan eksklusif sehubungan dengan pelaksanaan Pekerjaan dalam Kontrak ini. (2) Masing-masing Pihak akan menandatangani semua kontrak, dokumen, instrumen lain yang diminta oleh Pihak lain yang kemudian hari diperlukan untuk menyempurnakan Kontrak ini dan/atau kontrak-kontrak lain yang berhubungan dengan pelaksanaan Kontrak ini untuk mencapai tujuan Para Pihak sehubungan dengan hal yang diatur dalam Kontrak ini maupun dalam kontrak-kontrak lain yang berhubungan dengan Kontrak ini atau pemberitahuan atau dokumen, sertifikat dan/atau kelengkapan yang dimaksud di dalamnya dan/atau ditandatangani sehubungan dengan hal tersebut atau pernyataan lainnya yang diserahkan oleh Pihak yang satu terhadap Pihak lainnya. (3) Tidak ada dalam Kontrak ini yang memberikan hak apapun kepada setiap orang atau badan, yang bukan pihak dalam Kontrak ini, kecuali secara tegas diatur dalam Kontrak ini. (4) Kontrak ini akan mengikat atas dan untuk manfaat Para Pihak dalam hal ini dan masing-masing penerus dan penerima pengalihannya. Demikian Kontrak ini dibuat dalam 2 (dua) rangkap masing-masing bermeterai cukup dan mempunyai kekuatan hukum yang sama sebagai dokumen asli dan ditandatangani di Jakarta pada hari, tanggal, bulan, dan tahun sebagaimana disebutkan pada awal Kontrak ini oleh Para Pihak yang berwenang penuh. PIHAK KEDUA, PIHAK PERTAMA, [Tandatangan Pihak Kedua] [Tandatangan Pihak Pertama] [Nama] [Nama] | D97: Tanda tangan PIHAK KEDUA
D98: Nama PIHAK KEDUA
D99: Tanda tangan PIHAK PERTAMA
D100: Nama PIHAK PERTAMA

Sheet Syarat Umum Perjanjian Kontrak 
C1: Pengadaan Barang/Jasa Lainnya | D1: Pengadaan Jasa Konsultansi | E1: Pengadaan Jasa Konstruksi | F1: Pembelian Tenaga Listrik/Uap
C2: 0012.E/DIR/2023 | D2: 0010.E/DIR/2024 | E2: 0013.E/DIR/2024 | F2: 0037.E/DIR/2023
A3: Ketentuan Umum | B3: Definisi | C3: TRUE | D3: TRUE | E3: TRUE | F3: FALSE
B4: Penerapan | C4: TRUE | D4: TRUE | E4: TRUE | F4: FALSE
B5: Asal Barang/Jasa Lainnya | C5: TRUE | D5: FALSE | E5: TRUE | F5: FALSE
B6: Penggunaan Dokumen-Dokumen Perjanjian/Kontrak dan Informasi | C6: TRUE | D6: TRUE | E6: TRUE | F6: FALSE
B7: Hak Paten, Hak Cipta, dan Merek | C7: TRUE | D7: FALSE | E7: TRUE | F7: FALSE
B8: Jaminan | C8: TRUE | D8: FALSE | E8: TRUE | F8: FALSE
B9: Asuransi | C9: TRUE | D9: FALSE | E9: TRUE | F9: FALSE
B10: Pembayaran | C10: TRUE | D10: TRUE | E10: TRUE | F10: FALSE
B11: Harga | C11: TRUE | D11: TRUE | E11: TRUE | F11: FALSE
B12: Adendum/Amandemen Perjanjian/Kontrak | C12: TRUE | D12: TRUE | E12: TRUE | F12: FALSE
B13: Ketentuan Jadwal Pelaksanaan Pekerjaan | C13: TRUE | D13: TRUE | E13: TRUE | F13: FALSE
B14: Pengawasan | C14: TRUE | D14: TRUE | E14: TRUE | F14: FALSE
B15: Keterlambatan Pelaksanaan Pekerjaan | C15: TRUE | D15: TRUE | E15: TRUE | F15: FALSE
... B23: Korespondensi | C23: TRUE | D23: TRUE | E23: TRUE | F23: FALSE
A24: Ketentuan Umum Pembelian Tenaga Listrik/Uap | B24: Kriteria Pembelian Tenaga Listrik/Uap | C24: FALSE | D24: FALSE | E24: FALSE | F24: TRUE
B25: Persyaratan kualifikasi untuk menjadi PPL/Badan Usaha Penyedia Uap | C25: FALSE | D25: FALSE | E25: FALSE | F25: TRUE
B26: Pendayagunaan Produksi Dalam Negeri | C26: FALSE | D26: FALSE | E26: FALSE | F26: TRUE
B27: Metode Pembelian Tenaga Listrik/Uap | C27: FALSE | D27: FALSE | E27: FALSE | F27: TRUE
B28: Pola Kerja Sama | C28: FALSE | D28: FALSE | E28: FALSE | F28: TRUE
A29: Ketentuan Khusus | B29: Kewajiban Penyedia Jasa Konsultansi | C29: FALSE | D29: TRUE | E29: FALSE | F29: FALSE
B30: Personel Konsultan dan Subkonsultan | C30: FALSE | D30: TRUE | E30: FALSE | F30: FALSE
B31: Waktu Kerja dan Lembur | C31: FALSE | D31: TRUE | E31: FALSE | F31: FALSE
B32: Penggantian dan Perpindahan Personel | C32: FALSE | D32: TRUE | E32: FALSE | F32: FALSE
B33: Standar | C33: TRUE | D33: FALSE | E33: TRUE | F33: FALSE
B34: Pengepakan (Packaging) | C34: TRUE | D34: FALSE | E34: TRUE | F34: FALSE
B35: Pengiriman | C35: TRUE | D35: FALSE | E35: TRUE | F35: FALSE
B36: Transportasi | C36: TRUE | D36: FALSE | E36: TRUE | F36: FALSE
B37: Pemeriksaan dan Pengujian | C37: TRUE | D37: FALSE | E37: TRUE | F37: FALSE
B38: Layanan Tambahan | C38: TRUE | D38: FALSE | E38: TRUE | F38: FALSE
B39: Persetujuan Penempatan/Penggantian Personel | C39: FALSE | D39: FALSE | E39: TRUE | F39: FALSE
B40: Ketentuan atas Penemuan Benda/Barang Bernilai Sejarah atau Kekayaan Negara | C40: FALSE | D40: FALSE | E40: TRUE | F40: FALSE
B41: Ketentuan Kompensasi | C41: FALSE | D41: FALSE | E41: TRUE | F41: FALSE
... B43: Pedoman Pengoperasian dan Perawatan | C43: FALSE | D43: FALSE | E43: TRUE | F43: FALSE
A44: Ketentuan PJBL/PJBU *Muatan PJBL/PJBU dapat disesuaikan dengan adanya ketentuan khusus dan/atau disesuaikan dengan maksud dan tujuan pengembangan Pembangkit Energi Baru Terbarukan/Uap yang dimaksud. | B44: Jangka waktu PJBL/PJBU | C44: FALSE | D44: FALSE | E44: FALSE | F44: TRUE
B45: Hak dan kewajiban PPL/Badan Usaha Penyedia Uap selaku penjual dan PLN selaku pembeli | C45: FALSE | D45: FALSE | E45: FALSE | F45: TRUE
B46: Jaminan pelaksanaan proyek | C46: FALSE | D46: FALSE | E46: FALSE | F46: TRUE
B47: Project Development Cost Account (PDCA) | C47: FALSE | D47: FALSE | E47: FALSE | F47: TRUE
B48: Komisioning dan Commercial Operation Date (COD) | C48: FALSE | D48: FALSE | E48: FALSE | F48: TRUE
B49: Sertifikasi instalasi tenaga listrik | C49: FALSE | D49: FALSE | E49: FALSE | F49: TRUE
B50: Pasokan bahan bakar (apabila ada) | C50: FALSE | D50: FALSE | E50: FALSE | F50: TRUE
B51: Transaksi | C51: FALSE | D51: FALSE | E51: FALSE | F51: TRUE
B52: Pengendalian operasi sistem | C52: FALSE | D52: FALSE | E52: FALSE | F52: TRUE
B53: Liquidated damages terhadap ketidaksesuaian pelaksanaan PJBL/PJBU | C53: FALSE | D53: FALSE | E53: FALSE | F53: TRUE
B54: Pengakhiran PJBL/PJBU | C54: FALSE | D54: FALSE | E54: FALSE | F54: TRUE
B55: Pengalihan hak | C55: FALSE | D55: FALSE | E55: FALSE | F55: TRUE
B56: Harga | C56: FALSE | D56: FALSE | E56: FALSE | F56: TRUE
... B64: Persyaratan pemenuhan tanggal kejadian penting | C64: FALSE | D64: FALSE | E64: FALSE | F64: TRUE

Sheet Pemetaan Jenis Kontrak
B1: Kontrak Biaya Plus Imbalan | C1: Kontrak Gabungan | D1: Kontrak Harga Satuan | E1: Kontrak Kesepakatan Harga Satuan | F1: Kontrak Lumsum | G1: Kontrak Payung | H1: Kontrak Terima Jadi | I1: Kontrak Waktu Penugasan
A3: Identifier Perjanjian | B3: TRUE | C3: TRUE | D3: TRUE | E3: TRUE | F3: TRUE | G3: TRUE | H3: TRUE | I3: TRUE
A4: Dasar Pekerjaan | B4: TRUE | C4: TRUE | D4: TRUE | E4: TRUE | F4: TRUE | G4: TRUE | H4: TRUE | I4: TRUE
A5: Definisi | B5: TRUE | C5: TRUE | D5: TRUE | E5: TRUE | F5: TRUE | G5: TRUE | H5: TRUE | I5: TRUE
A6: Ruang Lingkup Pekerjaan/Perjanjian | B6: TRUE | C6: TRUE | D6: TRUE | E6: TRUE | F6: TRUE | G6: TRUE | H6: TRUE | I6: TRUE
A7: Harga Satuan | B7: FALSE | C7: FALSE | D7: FALSE | E7: TRUE | F7: FALSE | G7: FALSE | H7: FALSE | I7: FALSE
A8: Nilai Perjanjian | B8: TRUE | C8: TRUE | D8: TRUE | E8: FALSE | F8: TRUE | G8: TRUE | H8: TRUE | I8: TRUE
A9: Struktur Organisasi Pelaksanaan | B9: FALSE | C9: TRUE | D9: FALSE | E9: TRUE | F9: TRUE | G9: TRUE | H9: TRUE | I9: FALSE
A10: Jangka Waktu | B10: TRUE | C10: TRUE | D10: TRUE | E10: TRUE | F10: TRUE | G10: TRUE | H10: TRUE | I10: TRUE
A11: Hak, Kewajiban, dan Larangan | B11: TRUE | C11: TRUE | D11: TRUE | E11: FALSE | F11: TRUE | G11: TRUE | H11: TRUE | I11: TRUE
A12: Pola Pengawasan | B12: FALSE | C12: TRUE | D12: TRUE | E12: TRUE | F12: TRUE | G12: FALSE | H12: TRUE | I12: FALSE
A13: SLA & Kriteria Penilaian Pekerjaan | B13: FALSE | C13: TRUE | D13: TRUE | E13: TRUE | F13: TRUE | G13: TRUE | H13: TRUE | I13: TRUE
A14: Manajemen Mutu dan Sistem Verifikasi Kepatuhan | B14: FALSE | C14: TRUE | D14: TRUE | E14: TRUE | F14: TRUE | G14: FALSE | H14: TRUE | I14: FALSE
... A40: Korespondensi | B40: TRUE | C40: TRUE | D40: TRUE | E40: TRUE | F40: TRUE | G40: TRUE | H40: TRUE | I40: TRUE

Sheet Pemetaan Kontrak (backup)
B1: Kontrak Lumsum | F1: Kontrak Harga Satuan | I1: Kontrak Gabungan | L1: Kontrak Terima Jadi | O1: Kontrak Kesepakatan Harga Satuan | R1: Kontrak Payung | S1: Kontrak Waktu Penugasan | T1: Kontrak Biaya Plus Imbalan
B2: Barang | C2: Jasa Lainnya | D2: Jasa Konsultansi | E2: Pekerjaan Konstruksi | F2: Barang | G2: Jasa Lainnya | H2: Pekerjaan Konstruksi | I2: Barang | J2: Jasa Lainnya | K2: Pekerjaan Konstruksi | L2: Barang | M2: Jasa Lainnya | N2: Pekerjaan Konstruksi | O2: Barang | P2: Jasa Lainnya | Q2: Pekerjaan Konstruksi | R2: Jasa Konsultansi | S2: Jasa Konsultansi | T2: Barang | U2: Jasa Lainnya | V2: Pekerjaan Konstruksi
A3: Identifier Perjanjian | B3: TRUE | C3: TRUE | D3: TRUE | E3: TRUE | F3: TRUE | G3: FALSE | H3: FALSE | I3: TRUE | J3: FALSE | K3: FALSE | L3: TRUE | M3: FALSE | N3: FALSE | O3: TRUE | P3: FALSE | Q3: FALSE | R3: TRUE | S3: TRUE | T3: TRUE | U3: FALSE | V3: FALSE
A4: Dasar Pekerjaan | B4: TRUE | C4: TRUE | D4: TRUE | E4: TRUE | F4: TRUE | G4: FALSE | H4: FALSE | I4: TRUE | J4: FALSE | K4: FALSE | L4: TRUE | M4: FALSE | N4: FALSE | O4: TRUE | P4: FALSE | Q4: FALSE | R4: TRUE | S4: TRUE | T4: TRUE | U4: FALSE | V4: FALSE
A5: Definisi | B5: TRUE | C5: TRUE | D5: TRUE | E5: TRUE | F5: TRUE | G5: FALSE | H5: FALSE | I5: TRUE | J5: FALSE | K5: FALSE | L5: TRUE | M5: FALSE | N5: FALSE | O5: TRUE | P5: FALSE | Q5: FALSE | R5: TRUE | S5: TRUE | T5: TRUE | U5: FALSE | V5: FALSE
A6: Ruang Lingkup Pekerjaan/Perjanjian | B6: TRUE | C6: TRUE | D6: TRUE | E6: TRUE | F6: TRUE | G6: FALSE | H6: FALSE | I6: TRUE | J6: FALSE | K6: FALSE | L6: TRUE | M6: FALSE | N6: FALSE | O6: TRUE | P6: FALSE | Q6: FALSE | R6: TRUE | S6: TRUE | T6: TRUE | U6: FALSE | V6: FALSE
A7: Metodologi dan Tahapan Pelaksanaan Pekerjaan | B7: TRUE | C7: TRUE | D7: TRUE | E7: FALSE | F7: FALSE | G7: FALSE | H7: FALSE | I7: FALSE | J7: FALSE | K7: FALSE | L7: FALSE | M7: FALSE | N7: FALSE | O7: FALSE | P7: FALSE | Q7: FALSE | R7: FALSE | S7: FALSE | T7: FALSE | U7: FALSE | V7: FALSE
A8: Nilai Perjanjian | B8: TRUE | C8: TRUE | D8: TRUE | E8: TRUE | F8: TRUE | G8: FALSE | H8: FALSE | I8: TRUE | J8: FALSE | K8: FALSE | L8: TRUE | M8: FALSE | N8: FALSE | O8: FALSE | P8: FALSE | Q8: FALSE | R8: TRUE | S8: TRUE | T8: TRUE | U8: FALSE | V8: FALSE
A9: Harga Satuan | B9: FALSE | C9: FALSE | D9: FALSE | E9: FALSE | F9: FALSE | G9: FALSE | H9: FALSE | I9: FALSE | J9: FALSE | K9: FALSE | L9: FALSE | M9: FALSE | N9: FALSE | O9: TRUE | P9: FALSE | Q9: FALSE | R9: FALSE | S9: FALSE | T9: FALSE | U9: FALSE | V9: FALSE
A10: Non Harga Satuan | B10: TRUE | C10: TRUE | D10: TRUE | E10: TRUE | F10: FALSE | G10: FALSE | H10: FALSE | I10: FALSE | J10: FALSE | K10: FALSE | L10: FALSE | M10: FALSE | N10: FALSE | O10: FALSE | P10: FALSE | Q10: FALSE | R10: FALSE | S10: FALSE | T10: FALSE | U10: FALSE | V10: FALSE
A11: Struktur Organisasi Pelaksanaan | B11: TRUE | C11: TRUE | D11: TRUE | E11: TRUE | F11: FALSE | G11: FALSE | H11: FALSE | I11: TRUE | J11: FALSE | K11: FALSE | L11: TRUE | M11: FALSE | N11: FALSE | O11: TRUE | P11: FALSE | Q11: FALSE | R11: TRUE | S11: FALSE | T11: FALSE | U11: FALSE | V11: FALSE
A12: Jangka Waktu | B12: TRUE | C12: TRUE | D12: TRUE | E12: TRUE | F12: TRUE | G12: FALSE | H12: FALSE | I12: TRUE | J12: FALSE | K12: FALSE | L12: TRUE | M12: FALSE | N12: FALSE | O12: TRUE | P12: FALSE | Q12: FALSE | R12: TRUE | S12: TRUE | T12: TRUE | U12: FALSE | V12: FALSE
A13: Hak, Kewajiban, dan Larangan | B13: TRUE | C13: TRUE | D13: TRUE | E13: TRUE | F13: TRUE | G13: FALSE | H13: FALSE | I13: TRUE | J13: FALSE | K13: FALSE | L13: TRUE | M13: FALSE | N13: FALSE | O13: FALSE | P13: FALSE | Q13: FALSE | R13: TRUE | S13: TRUE | T13: TRUE | U13: FALSE | V13: FALSE
A14: Pola Pengawasan | B14: FALSE | C14: FALSE | D14: FALSE | E14: TRUE | F14: TRUE | G14: FALSE | H14: FALSE | I14: TRUE | J14: FALSE | K14: FALSE | L14: TRUE | M14: FALSE | N14: FALSE | O14: TRUE | P14: FALSE | Q14: FALSE | R14: FALSE | S14: FALSE | T14: FALSE | U14: FALSE | V14: FALSE
... A54: Penutup | B54: TRUE | C54: TRUE | D54: TRUE | E54: TRUE | F54: FALSE | G54: FALSE | H54: FALSE | I54: FALSE | J54: FALSE | K54: FALSE | L54: FALSE | M54: FALSE | N54: FALSE | O54: FALSE | P54: FALSE | Q54: FALSE | R54: FALSE | S54: FALSE | T54: FALSE | U54: FALSE | V54: FALSE

Sheet Master Klausul (backup)
B1: Klausul | C1: Data
A2: Header | B2: Perjanjian/Kontrak [Nomor Perjanjian/Kontrak] tentang [Nama Pekerjaan] Antara PT PLN (Persero) dengan [Nama Penyedia Barang/Jasa] | C2: Nomor Perjanjian
C3: Nama Pekerjaan
C4: Nama Penyedia Barang/Jasa
A5: ='Pemetaan Kontrak '!B9 -> Identifier Perjanjian | B5: Perjanjian [Nama Pekerjaan] berikut semua lampirannya dibuat dan disepakati di [Tempat Perjanjian/Kontrak] pada hari [Hari Penandatanganan] tanggal [Tanggal Penandatanganan] oleh dan antara: I. PT PLN (Persero) : Suatu Perseroan Terbatas yang didirikan berdasarkan hukum Republik Indonesia berdasarkan Akta Nomor 169 tanggal 30 Juli 1994, dibuat oleh dan dihadapan Sutjipto, S.H. Notaris di Jakarta, yang telah diubah beberapa kali, terakhir dilakukan perubahan sebagaimana Akta No. 12 tanggal 25 Maret 2021 dibuat oleh dan dihadapan Lenny Janis Ishak, SH. Notaris di Jakarta, yang dalam hal ini di wakili oleh [Nama pejabat yang menandatangani] selaku [Jabatan Penandatangan] PT PLN (Persero) [Nama Unit] berdasarkan Keputusan Direksi PT PLN (Persero) Nomor: [Nomor KepDir] tentang [Judul KepDir], sehingga dalam hal ini berhak dan berwenang bertindak untuk dan atas nama PT PLN (Persero), berkedudukan di [Nama Unit], untuk selanjutnya disebut sebagai PIHAK PERTAMA II. [Nama Penyedia Barang/Jasa] : Suatu [Bentuk Badan Usaha] yang didirikan berdasarkan Hukum Republik Indonesia berdasarkan Akta No. [Nomor Akta Pendirian Perusahaan] tanggal [Tanggal Akta Pendirian] dibuat oleh dan dihadapan [Nama Notaris Pembuat Akta], Notaris di [Kota Notaris], yang telah diubah beberapa kali, terakhir dilakukan perubahan sebagaimana Akta Nomor [Nomor Akta Perubahan Terakhir] tanggal [Tanggal Perubahan Terakhir] dibuat oleh dan dihadapan [Nama Notaris Pembuat Akta], Notaris di [Kota Notaris] yang dalam hal ini diwakili oleh [Nama perwakilan perusahaan] selaku [Jabatan perwakilan] sehingga dalam hal ini berhak dan bewenang bertindak untuk dan atas nama [Nama Penyedia Barang/Jasa], berkedudukan di [Alamat/Kota Domisili Penyedia Barang/Jasa], untuk selanjutnya disebut sebagai PIHAK KEDUA Untuk selanjutnya PIHAK PERTAMA dan PIHAK KEDUA secara sendiri-sendiri disebut PIHAK dan secara Bersama-sama disebut PARA PIHAK. | C5: Nama Pekerjaan
C6: Tempat Perjanjian
C7: Hari penandatanganan
C8: Tanggal Penandatanganan
C9: Nama pejabat yang menandatangani
C10: Nama Unit
C11: Nomor KepDir
C12: Judul KepDir
C13: Nama Penyedia Barang/Jasa
C14: Bentuk Badan Usaha
C15: Nomor Akta Pendirian Perusahaan
C16: Tanggal Akta Pendirian
C17: Nama Notaris Pembuat Akta
... C22: Alamat/kota domisili Penyedia Barang/Jasa
A23: ='Pemetaan Kontrak '!B10 -> Dasar Pekerjaan | B23: 1. PIHAK PERTAMA dalam menjalankan kegiatan operasionalnya, melakukan [jenis pengadaan] dengan mengacu pada: a. [list] Peraturan 2. PIHAK KEDUA telah menyetujui untuk melaksanakan pekerjaan [Jenis Pengadaan] sesuai dengan persyaratan dan ketentuan dalam Perjanjian/Kontrak ini sesuai dengan dokumen-dokumen sebagaimana berikut: a. Dokumen Tender/RKS No. [Nomor dokumen tender/RKS], tanggal [Tanggal dokumen tender/RKS] beserta addendumnya [apabila ada]. b. Surat Penawaran Sampul 1 (Administrasi dan Teknis) No. [Nomor surat administrasi & teknis] tanggal [Tanggal surat penawaran sampul 1] c. Surat Penawaran Sampul 2 (Harga) No. [Nomor surat penawaran harga] tanggal [Tanggal surat penawaran sampul 2] d. Surat Penunjukan Penyedia Barang/Jasa No. [Nomor SPPBJ/SPPBJ] tanggal [Tanggal surat penunjukan] e. Surat Perintah Mulai Kerja No. [Nomor Surat Perintah Mulai Kerja] tanggal [Tanggal Surat Perintah Mulai Kerja] f. Kesepakatan Diskusi Perjanjian (Contract Discussion Agreement) tanggal [Tanggal Contract Discussion Agreement] g. [Dokumen pendukung tambahan (jika dibutuhkan)] Berdasarkan hal-hal tersebut, maka PARA PIHAK dengan ini sepakat untuk mengikatkan diri dalam sebuah Perjanjian/Kontrak yang berisi syarat-syarat dan ketentuan-ketentuan sebagai berikut: | C23: [list] Peraturan
C24: Jenis Pengadaan
C25: Nomor Dokumen Tender/RKS
C26: Tanggal Dokumen Tender/RKS
C27: Nomor surat administrasi & teknis
C28: Tanggal surat penawaran sampul 1
C29: Nomor surat penawaran harga
C30: Tanggal surat penawaran sampul 2
C31: Nomor SPPBJ/SPPBJ
C32: Tanggal surat penunjukan
C33: Nomor Surat Perintah Mulai Kerja
C34: Tanggal Surat Perintah Mulai Kerja
C35: Tanggal Contract Discussion Agreement
C36: Dokumen pendukung tambahan (jika dibutuhkan)
A37: ='Pemetaan Kontrak '!B11 -> Definisi | B37: 1. Berita Acara Serah Terima Pekerjaan (BASTP) adalah berita acara yang dibuat setelah progres fisik pekerjaan mencapai 100% (seratus persen). 2. Berita Acara Penyerahan Akhir (BAP-Akhir) adalah berita acara yang dibuat untuk menyatakan Hak dan Kewajiban para pihak telah selesai seluruhnya sehingga Perjanjian dinyatakan ditutup. 3. Direksi Pekerjaan adalah Pejabat yang diberi wewenang untuk mengawasi pelaksanaan pekerjaan berdasarkan Perjanjian/Kontrak. [mengikuti definisi tercantum dalam Perdir Nomor 0018.P/DIR/2023 dan sesuai jenis Pengadaan] | C37: Mengikuti definisi tercantum dalam Perdir Nomor 0018.P/DIR/2023 dan sesuai jenis Pengadaan
A38: ='Pemetaan Kontrak '!B12 -> Ruang Lingkup Pekerjaan/Perjanjian | B38: 1. PIHAK PERTAMA memberikan pekerjaan kepada PIHAK KEDUA untuk melaksanakan [Jenis Pengadaan] [Nama Pekerjaan] dan PIHAK KEDUA menerima penugasan tersebut. 2. Uraian [Jenis Pengadaan] tersebut di atas tercantum sebagaimana Lampiran 1 ini dan/atau sesuai dengan Dokumen Pengadaan yang telah ditentukan PIHAK PERTAMA. | C38: Jenis Pengadaan
C39: Nama Pekerjaan
A40: ='Pemetaan Kontrak '!B13 -> Metodologi dan Tahapan Pelaksanaan Pekerjaan | B40: 1. | C40: Freetext
A41: ='Pemetaan Kontrak '!B14 -> Nilai Perjanjian
A42: KHS | B42: 1. Sumber dana yang digunakan dalam pelaksanaan Pekerjaan Perjanjian/Kontrak adalah [APLN/Pinjaman/Hibah Luar Negeri/Pinjaman/Hibah Dalam Negeri]. 2. Harga Satuan adalah sebagaimana ditetapkan pada Perjanjian/Kontrak ini berlaku dan mengikat Para Pihak untuk jangka waktu 1 (satu) tahun atau sepanjang Jangka Waktu Penerbitan. 3. Jenis Perjanjian/Kontrak untuk pekerjaan ini adalah [Jenis Perjanjian/Kontrak]. | C42: Sumber Dana [APLN/Pinjaman/Hibah Luar Negeri/Pinjaman/Hibah Dalam Negeri]
C43: Jenis Perjanjian/Kontrak
A44: Harga Satuan | B44: 1. Sumber dana yang digunakan dalam pelaksanaan Pekerjaan Perjanjian/Kontrak adalah [APLN/Pinjaman/Hibah Luar Negeri/Pinjaman/Hibah Dalam Negeri]. 2. Harga Satuan adalah sebagaimana ditetapkan pada Perjanjian/Kontrak ini berlaku dan mengikat Para Pihak untuk jangka waktu 1 (satu) tahun atau sepanjang Jangka Waktu Penerbitan. 3. PIHAK KEDUA akan melaksanakan Pekerjaan sesuai dengan spesifikasi pada ayat (1) Pasal ini dengan mempertimbangkan volume dan satuan lainnya bersifat indikatif sesuai dengan Lampiran 1 Perjanjian ini. 4. Jenis Perjanjian/Kontrak untuk pekerjaan ini adalah [Jenis Perjanjian/Kontrak]. | C44: Sumber Dana [APLN/Pinjaman/Hibah Luar Negeri/Pinjaman/Hibah Dalam Negeri]
C45: Jenis Perjanjian/Kontrak
A46: ='Pemetaan Kontrak '!B17 -> Non Harga Satuan | B46: 1. Sumber dana yang digunakan dalam pelaksanaan Pekerjaan Perjanjian/Kontrak adalah [APLN/Pinjaman/Hibah Luar Negeri/Pinjaman/Hibah Dalam Negeri]. 2. Nilai Total Perjanjian/Kontrak untuk Pekerjaan [Nama Pekerjaan] ini adalah sebagaimana dirinci dibawah ini a. Nilai Perjanjian/Kontrak : [mata uang yang disepakati oleh Para Pihak][Nilai nominal Perjanjian/Kontrak] ([terbilang]) Nilai tukar [Mata uang yang disepakati oleh Para Pihak] yang digunakan sebagai Nilai Perjanjian ditetapkan berdasarkan [Kurs tengah/JISDOR dari Bank Indonesia] yang berlaku pada tanggal [Tanggal kurs yang digunakan]; b. Pajak Pertambahan Nilai [Persentase Pajak Pertambahan Nilai]% dari Nilai Perjanjian/Kontrak : [mata uang yang disepakati oleh Para Pihak] [Nilai PPN nominal] ([terbilang]) Nilai Total Perjanjian/Kontrak : [Rp/USD/mata uang yang disepakati oleh Para Pihak][Total nilai Perjanjian/Kontrak setelah pajak] ([terbilang]) 3. Jenis Perjanjian/Kontrak untuk pekerjaan ini adalah [Jenis Perjanjian/Kontrak]. | C46: Sumber Dana [APLN/Pinjaman/Hibah Luar Negeri/Pinjaman/Hibah Dalam Negeri]
C47: Nama Pekerjaan
C48: Mata uang
C49: Nilai nominal Perjanjian/Kontrak
C50: Kurs tengah/JISDOR dari Bank Indonesia
C51: Tanggal kurs yang digunakan
C52: Persentase
C53: Persentase Pajak Pertambahan Nilai
C54: Nilai PPN Nominal
C55: Total nilai Perjanjian/Kontrak setelah pajak
C56: Jenis Perjanjian/Kontrak
A57: ='Pemetaan Kontrak '!B19 -> Struktur Organisasi Pelaksanaan | B57: 1. PIHAK PERTAMA menunjuk [Nama Jabatan] [Nama Unit] sebagai Direksi Pekerjaan untuk melakukan pengendalian dan pengawasan pelaksanaan dan/atau penyerahan pekerjaan serta bertanggungjawab untuk menyelesaikan semua administrasi, dan semua Berita Acara yang diperlukan terkait dengan proses tagihan (pembayaran) yang berkaitan dengan Perjanjian/Kontrak ini. 2. Apabila petugas yang ditunjuk tersebut dalam Ayat 1 Pasal ini berhalangan atau tidak dapat menjalankan kewajibannya, maka PIHAK PERTAMA akan menunjuk penggantinya dan akan disampaikan kepada PIHAK KEDUA secara tertulis. 3. Direksi Pekerjaan berhak untuk memberikan petunjuk-petunjuk/pengarahan kepada PIHAK KEDUA dalam melaksanakan pekerjaan sehari-hari. | C57: Nama Jabatan
C58: Nama Unit
A59: ='Pemetaan Kontrak '!B20 -> Jangka Waktu | B59: 1. Jangka waktu pelaksanaan [Jenis Pengadaan] yang diatur dalam Pasal [Nomor pasal yang mengatur ruang lingkup/ketentuan pekerjaan] Perjanjian/Kontrak ini harus diselesaikan oleh PIHAK KEDUA paling lambat [durasi pelaksanaan Perjanjian/Kontrak] Hari Kalender, dihitung mulai dari [tanggal penandatanganan Perjanjian/Kontrak ini/tanggal penyerahan Jaminan Pelaksanaan oleh PIHAK KEDUA kepada PIHAK PERTAMA], yaitu tanggal [Tanggal mulai efektif pelaksanaan]. 2. Apabila diperlukan, Perjanjian/Kontrak ini dapat diperpanjang oleh PARA PIHAK melalui kesepakatan bersama sebelum berakhirnya periode Perjanjian/Kontrak. Perpanjangan tersebut akan dituangkan dalam bentuk amandemen atau dokumen tertulis lainnya. 3. Pihak yang ingin memperpanjang Perjanjian/Kontrak harus mengirimkan pemberitahuan tertulis yang disertai dengan penjelasan yang rinci kepada pihak lainnya tidak lebih dari [jumlah hari batas perpanjangan] Hari Kalender sebelum kontrak berakhir. Pihak lainnya harus memberikan keputusan mengenai persetujuan perpanjangan Perjanjian/Kontrak dalam waktu [jumlah hari Tenggat pemberian keputusan persetujuan] Hari Kalender. Jika tidak ada keputusan persetujuan perpanjangan Perjanjian/Kontrak dalam jangka waktu yang ditentukan dalam ayat ini, maka Perjanjian/Kontrak akan dianggap berakhir. | C59: Jenis pengadaan
C60: Nomor pasal yang mengatur ruang lingkup/ketentuan pekerjaan
C61: Durasi Pelaksanaan Perjanjian/Kontrak
C62: Tanggal penandatanganan Perjanjian/Kontrak ini/tanggal penyerahan Jaminan Pelaksanaan oleh PIHAK KEDUA kepada PIHAK PERTAMA
C63: Tanggal mulai efektif pelaksanaan
C64: jumlah hari batas perpanjangan
C65: jumlah hari Tenggat pemberian keputusan persetujuan
A66: ='Pemetaan Kontrak '!B21 -> Hak, Kewajiban, dan Larangan | B66: 1. Hak PIHAK PERTAMA dalam pelaksanaan Perjanjian: a. PIHAK PERTAMA berhak mendapatkan hasil pekerjaan yang dilaksanakan oleh PIHAK KEDUA dengan kualitas dan kuantitas sesuai dengan ditentukan oleh PIHAK PERTAMA dalam Perjanjian ini. b. PIHAK PERTAMA berhak mendapatkan hasil pekerjaan dari PIHAK KEDUA sesuai dengan jangka waktu pelaksanaan pekerjaan yang diatur sebagaimana pada Pasal [Nomor pasal] Perjanjian ini. c. PIHAK PERTAMA berhak meminta kepada PIHAK KEDUA tenaga kerja yang memiliki keahlian dan keterampilan di bidangnya untuk melaksanakan pekerjaan. d. PIHAK PERTAMA berhak mengenakan sanksi kepada PIHAK KEDUA apabila PIHAK KEDUA tidak dapat melaksanakan ketentuan-ketentuan dalam Perjanjian ini. e. PIHAK PERTAMA berhak memutus Perjanjian ini secara sepihak apabila PIHAK KEDUA tidak dapat melaksanakan ketentuan-ketentuan dalam Perjanjian ini. 2. Kewajiban PIHAK PERTAMA dalam pelaksanaan Perjanjian: a. PIHAK PERTAMA wajib melakukan pembayaran berupa biaya aktual dan imbalan kepada PIHAK KEDUA atas hasil pelaksanaan pekerjaan yang telah dilaksanakan oleh PIHAK KEDUA sesuai dengan Perjanjian/Kontrak. b. PIHAK PERTAMA wajib memberikan instruksi dan/atau arahan kepada PIHAK KEDUA terkait pelaksanaan pekerjaan. 3. Hak PIHAK KEDUA dalam pelaksanaan Perjanjian/Kontrak: a. PIHAK KEDUA berhak menerima pembayaran berupa biaya aktual dan imbalan dari PIHAK PERTAMA atas hasil pelaksanaan yang telah dilaksanakan oleh PIHAK KEDUA. b. PIHAK KEDUA berhak menerima instruksi dan/atau arahan dari PIHAK PERTAMA sesuai jadwal pelaksanaan pekerjaan kepada PIHAK KEDUA terkait pelaksanaan pekerjaan yang telah ditetapkan dalam Perjanjian/Kontrak. 4. Kewajiban PIHAK KEDUA dalam pelaksanaan Perjanjian/Kontrak: a. PIHAK KEDUA wajib melaksanakan dan menyelesaikan pekerjaan dengan kualitas dan kuantitas sesuai dengan uraian pekerjaan yang telah diatur dalam Perjanjian/Kontrak ini. b. PIHAK KEDUA wajib menyelesaikan dan menyerahkan hasil pekerjaan sesuai dengan jangka waktu pelaksanaan pekerjaan yang diatur sebagaimana pada Pasal [Nomor pasal yang mengatur jangka waktu pelaksanaan] Perjanjian/Kontrak ini. c. PIHAK KEDUA wajib membuat dan menyampaikan kepada PIHAK PERTAMA laporan hasil pekerjaan. d. PIHAK KEDUA wajib melaksanakan ketentuan Keselamatan dan Kesehatan Kerja (K3) serta Pengamanan sebagaimana diatur pada Perjanjian/Kontrak ini. e. PIHAK KEDUA wajb melaksanakan ketentuan kelestarian lingkungan dan fasilitas sebagaimana diatur pada Perjanjian/Kontrak ini. f. PIHAK KEDUA wajib menggunakan tenaga kerja yang memiliki keahlian dan keterampilan di bidangnya untuk melaksanakan pekerjaan. g. PIHAK KEDUA bertanggung jawab dalam mendapatkan seluruh izin-izin yang diperlukan untuk kelancaran pekerjaan dan seluruh biaya yang timbul menjadi tanggung jawab PIHAK KEDUA. | C66: Nomor pasal
A67: ='Pemetaan Kontrak '!B22 -> Pola Pengawasan | B67: 1. PIHAK PERTAMA berhak melakukan pengawasan terhadap pelaksanaan Pekerjaan yang diwakili oleh Direksi Pekerjaan dibantu oleh Pengawas Pekerjaan. 2. Direksi Pekerjaan melakukan pemeriksaan atas Pekerjaan yang telah diserahkan oleh PIHAK KEDUA kepada PIHAK PERTAMA dengan melakukan pengendalian pelaksanaan Pekerjaan di lapangan, agar pelaksanaan Pekerjaan sesuai dengan ruang lingkup Perjanjian/Kontrak ini sebagaimana Lampiran 1. 3. Direksi Pekerjaan akan menyusun detil pelaksanaan Pekerjaan yang meliputi uraian Pekerjaan beserta jangka waktu dari masing-masing uraian Pekerjaan. 4. Apabila dalam pemeriksaan pekerjaan terdapat rusak/cacat atau tidak sesuai dengan syarat yang telah ditentukan, maka Direksi Pekerjaan memberitahukan secara tertulis kepada PIHAK KEDUA selambat-lambatnya [jumlah hari Tenggat waktu pemberitahuan ketidaksesuaian/cacat pekerjaan] ([terbilang]) Hari Kalender sejak diketahui adanya ketidaksesuaian dengan syarat yang ditentukan. 5. PIHAK KEDUA diberikan kesempatan untuk melakukan perbaikan Pekerjaan sebagaimana dimaksud ayat (4) Pasal ini dalam jangka waktu selambat-lambatnya [jumlah hari Waktu perbaikan pekerjaan oleh PIHAK KEDUA] Hari Kalender sejak PIHAK KEDUA menerima pemberitahuan tertulis dari PIHAK PERTAMA. | C67: Jumlah Hari Tenggat waktu pemberitahuan ketidaksesuaian/cacat pekerjaan
C68: Jumlah Hari Waktu perbaikan pekerjaan oleh PIHAK KEDUA
A69: ='Pemetaan Kontrak '!B23 -> Manajemen Mutu dan Sistem Verifikasi Kepatuhan | B69: 1. PIHAK KEDUA wajib menjamin bahwa seluruh produk dan layanan yang disediakan sesuai dengan standar mutu yang telah disepakati dalam Perjanjian ini. 2. PIHAK KEDUA wajib memiliki dan menjalankan Sistem Manajemen Mutu dengan standar internasional (seperti ISO 9001) untuk memastikan kepatuhan terhadap persyaratan mutu yang berlaku. 3. PIHAK KEDUA wajib memberikan akses kepada PIHAK PERTAMA untuk melakukan verifikasi kepatuhan terhadap standar mutu yang telah ditetapkan. 4. Verifikasi kepatuhan dapat dilakukan melalui audit, inspeksi atau metode verifikasi lainnya yang telah disepakati oleh PARA PIHAK. | C69: -
A70: ='Pemetaan Kontrak '!B24 -> Hasil dan Laporan | B70: Hasil pekerjaan atas Perjanjian ini yang harus diserahkan kepada PIHAK KEDUA kepada PIHAK PERTAMA adalah sebagai berikut: 1. | C70: Freetext
A71: ='Pemetaan Kontrak '!B25 -> Lokasi Pekerjaan | B71: Lokasi pelaksanaan atau tempat penyerahan hasil pekerjaan adalah di PT PLN (Persero) [Nama Unit], [Alamat Unit] | C71: Nama Unit
C72: Alamat Unit
A73: ='Pemetaan Kontrak '!B26 -> Jaminan
A74: ='Pemetaan Kontrak '!B27 -> Jaminan Uang Muka | B74: 1. Jaminan Uang Muka adalah sebesar [nominal yang minimal sama dengan nilai uang muka yang dibayarkan PIHAK PERTAMA kepada PIHAK KEDUA]. 2. Jaminan Uang Muka ditetapkan untuk menjamin kelancaran pembiayaan pekerjaan yang akan dilakukan oleh PIHAK KEDUA. 3. Masa berlaku Jaminan Uang Muka berlaku sejak tanggal pembayaran uang muka oleh PIHAK PERTAMA kepada PIHAK KEDUA sampai dengan tanggal [tanggal pelunasan uang muka] yang telah ditetapkan oleh PARA PIHAK. | C74: [nominal Jaminan Uang Muka]
C75: Tanggal pelunasan uang muka
A76: ='Pemetaan Kontrak '!B28 -> Jaminan Pelaksanaan | B76: 1. Jaminan Pelaksanaan diserahkan dari PIHAK KEDUA kepada PIHAK PERTAMA paling lambat 14 (empat belas) hari kerja setelah Perjanjian ditandatangani dan menjadi syarat efektif Perjanjian ini. 2. Apabila sampai dengan batas waktu yang ditetapkan, Jaminan Pelaksanaan belum diserahkan, maka Perjanjian ini dapat dibatalkan sepihak oleh PIHAK PERTAMA, dan PIHAK KEDUA yang ditunjuk dapat dikenakan sanksi Daftar Hitam (Blacklist) serta Jaminan Penawaran (jika ada) dicairkan dan menjadi milik PIHAK PERTAMA. 3. Jaminan Pelaksanaan dari Bank Umum (tidak termasuk Bank Perkreditan Rakyat) atau bank asing yang beroperasi di Indonesia/mempunyai perwakilan di Indonesia atau Lembaga Pembiayaan Ekspor Indonesia dan bukan yang diterbitkan oleh Perusahaan Asuransi yang terdapat dalam Daftar Penerbit Jaminan Terseleksi seperti terlampir, atas nama Perusahaan yang menawarkan, ditujukan kepada PT PLN (Persero) Kantor Pusat [Nama Unit], [Alamat Unit]. 4. Jaminan pelaksanaan sebesar minimal 5% (lima persen) dari nilai Perjanjian ini. 5. Masa berlaku Jaminan Pelaksanaan sejak tanggal diterbitkannya Jaminan sampai dengan sekurang-kurangnya waktu Serah Terima Pekerjaan Pertama dengan masa klaim selambat-lambatnya 14 (empat belas) hari setelah berakhirnya Jaminan Pelaksanaan. 6. Jaminan Pelaksanaan menjadi milik PIHAK PERTAMA dalam hal: 6.1. PIHAK KEDUA mengundurkan diri setelah menandatangani surat Perjanjian. 6.2. PIHAK KEDUA dalam waktu yang telah ditetapkan tidak melaksanakan/menyelesaikan pekerjaan atau terjadi pemutusan kontrak yang diakibatkan kelalaian PIHAK KEDUA. 7. Jaminan Pelaksanaan dapat dikembalikan setelah waktu Serah Terima Pekerjaan. 8. Jaminan Pelaksanaan bersifat tanpa syarat (unconditional) dan tidak dapat dialihkan (non-transferable). 9. Jaminan Pelaksanaan dicairkan dan menjadi milik PIHAK PERTAMA apabila dilakukan pemutusan Perjanjian. 10. Dalam hal pelaksanaan pekerjaan belum selesai dan memerlukan perpanjangan waktu pelaksanaan, maka PIHAK KEDUA wajib bersedia untuk memperpanjang masa berlaku Jaminan Pelaksanaan. 11. Dalam hal PIHAK KEDUA tidak bersedia memperpanjang masa berlaku Jaminan Pelaksanaan, maka PIHAK KEDUA tersebut dianggap wanprestasi dan Jaminan Pelaksanaan dicairkan dan menjadi milik PIHAK PERTAMA. | C76: Nama Unit
C77: Alamat Unit
A78: ='Pemetaan Kontrak '!B29 -> Jaminan Pemeliharaan | B78: 1. Format Jaminan Pemeliharaan sesuai dengan format yang ditetapkan oleh Penerbit Jaminan. 2. PIHAK KEDUA wajib menyerahkan Jaminan Pemeliharaan kepada PIHAK PERTAMA, minimal [nilai Persen]% [nilai Jaminan] dari Nilai Perjanjian, paling lambat diserahkan pada saat Berita Acara Serah Terima Pekerjaan ditandatangani dan menjadi syarat efektif untuk pembayaran. 3. Masa Pemeliharaan adalah [Jumlah Bulan] bulan sejak tanggal ditandatanganinya Berita Acara Serah Terima Pekerjaan. 4. Jaminan Pemeliharaan ditetapkan untuk menjamin kualitas Pekerjaan yang diserahkan, dipersyaratkan untuk pekerjaan yang memerlukan Masa Pemeliharaan. 5. PIHAK PERTAMA menerima akhir pekerjaan setelah PIHAK KEDUA melaksanakan semua kewajibannya selama Masa Pemeliharaan dengan baik yang dibuktikan dengan penandatanganan Berita Acara Selesainya Masa Pemeliharaan. 6. Masa berlaku Jaminan Pemeliharaan adalah sejak tanggal penerbitan Jaminan Pemeliharaan sampai dengan tanggal Berita Acara Selesainya Masa Pemeliharaan. 7. Selama Masa Pemeliharaan, PIHAK KEDUA harus menjaga dan mempertahankan hasil pekerjaan yang telah dilaksanakan sehingga tetap seperti kondisi pada saat dilakukan serah terima pekerjaan sebagaimana Berita Acara Serah Terima Pekerjaan (BASTP). 8. Apabila selama Masa Pemeliharaan terdapat kerusakan terhadap hasil pekerjaan maka PIHAK KEDUA harus melaksanakan perbaikan pekerjaan sehingga hasil pekerjaan sesuai dengan spesifikasi material dan syarat-syarat teknis sebagaimana telah ditentukan oleh PIHAK PERTAMA. 9. Apabila selama Masa Pemeliharaan telah selesai dan PIHAK KEDUA telah melaksanakan apa yang menjadi kewajibannya selama Masa Pemeliharaan, maka PIHAK KEDUA mengajukan secara tertulis kepada PIHAK PERTAMA untuk dilakukan penyerahan akhir pekerjaan. 10. Sebelum dilakukan penyerahan akhir pekerjaan, atau Direksi Pekerjaan akan melakukan pemeriksaan terhadap hasil pekerjaan yang dilakukan oleh PIHAK KEDUA selama masa pemeliharaan ini. Apabila hasil pemeriksaan pengawas pekerjaan dan/ atau Direksi Pekerjaan terhadap hasil pekerjaan PIHAK KEDUA telah sesuai sebagaimana dimaksud pada Perjanjian ini, maka PIHAK PERTAMA akan menerima penyerahan akhir pekerjaan tersebut yang dituangkan dalam Berita Acara Penyerahan Akhir Pekerjaan yang ditandatangani oleh PARA PIHAK dan Direksi Pekerjaan. | C78: Nilai Persen
C79: Nilai Jaminan
C80: Jumlah Bulan Pemeliharaan
A81: ='Pemetaan Kontrak '!B30 -> Retensi | B81: 1. Selama Masa Pemeliharaan, PIHAK KEDUA harus menjaga dan mempertahankan hasil pekerjaan yang telah dilaksanakan sehingga tetap seperti kondisi pada saat dilakukan serah terima pekerjaan sebagaimana Berita Acara Serah Terima Pekerjaan (BASTP). 2. Apabila selama Masa Pemeliharaan terdapat kerusakan terhadap hasil pekerjaan maka PIHAK KEDUA harus melaksanakan perbaikan pekerjaan sehingga hasil pekerjaan sesuai dengan spesifikasi material dan syarat-syarat teknis sebagaimana telah ditentukan oleh PIHAK PERTAMA. 3. Apabila selama Masa Pemeliharaan telah selesai dan PIHAK KEDUA telah melaksanakan apa yang menjadi kewajibannya selama Masa Pemeliharaan, maka PIHAK KEDUA mengajukan secara tertulis kepada PIHAK PERTAMA untuk dilakukan penyerahan akhir pekerjaan. 4. Sebelum dilakukan penyerahan akhir pekerjaan, atau Direksi Pekerjaan akan melakukan pemeriksaan terhadap hasil pekerjaan yang dilakukan oleh PIHAK KEDUA selama masa pemeliharaan ini. Apabila hasil pemeriksaan pengawas pekerjaan dan/ atau Direksi Pekerjaan terhadap hasil pekerjaan PIHAK KEDUA telah sesuai sebagaimana dimaksud pada Perjanjian ini, maka PIHAK PERTAMA akan menerima penyerahan akhir pekerjaan tersebut yang dituangkan dalam Berita Acara Penyerahan Akhir Pekerjaan yang ditandatangani oleh PARA PIHAK dan Direksi Pekerjaan. | C81: -
A82: ='Pemetaan Kontrak '!B31 -> Pembayaran
A83: ='Pemetaan Kontrak '!B32 -> Full | B83: 1. Pembayaran dilakukan oleh PIHAK PERTAMA kepada PIHAK KEDUA dengan mata uang [Mata Uang]. 2. Pembayaran akan dilakukan oleh PIHAK PERTAMA setelah menerima permintaan pembayaran dari PIHAK KEDUA yang dilengkapi dokumen-dokumen: 3.1. Surat Permohonan Pembayaran. 3.2. Berita Acara Pemeriksaan Pekerjaan yang ditandatangani oleh Pengawas Pekerjaan dan PIHAK KEDUA serta diketahui oleh Direksi Pekerjaan. 3.3. Berita Acara Serah Terima Pekerjaan yang ditandatangani oleh Direksi Pekerjaan dan PIHAK KEDUA serta ditandatangani oleh PIHAK PERTAMA. 3.4. Kuitansi 4 (empat) rangkap, bermeterai secukupnya. 3.5. e-faktur pajak. 3.6. Fotokopi Nomor Pokok Wajib Pajak (NPWP). 3.7. Fotokopi Pengukuhan Pengusaha Kena Pajak (PKP). 3.8. Fotokopi Perjanjian. 3. Pembayaran akan dilakukan oleh PIHAK PERTAMA dengan cara transfer ke rekening PIHAK KEDUA sebagaimana berikut: Nama Bank : ______________ No. Rekening : _____________ Atas Nama : << NAMA VENDOR >> | C83: Mata Uang
C84: Nama Bank
C85: No Rekening
C86: Atas Nama
A87: ='Pemetaan Kontrak '!B33 -> Termin | B87: 1. Pembayaran dilakukan dengan tahapan sebagai berikut: 2.1. TAHAP I: pembayaran dilakukan sebesar [Persentase pembayaran termin pertama]% dari Nilai Pekerjaan ditambah PPN sesuai peraturan yang berlaku, setelah PIHAK KEDUA [Kondisi/milestone pembayaran tahap 1] 2.2. TAHAP II: pembayaran dilakukan sebesar [Persentase pembayaran termin kedua]% dari Nilai Pekerjaan ditambah PPN sesuai peraturan yang berlaku, setelah PIHAK KEDUA [Kondisi/milestone pembayaran tahap 2] (Jumlah Tahap menyesuaikan Jumlah Termin) 2. Pembayaran akan dilakukan oleh PIHAK PERTAMA setelah menerima permintaan pembayaran dari PIHAK KEDUA yang dilengkapi dokumen-dokumen: 2.1. Surat Permohonan Pembayaran. 2.2. Berita Acara Pemeriksaan Pekerjaan yang ditandatangani oleh Pengawas Pekerjaan dan PIHAK KEDUA serta diketahui oleh Direksi Pekerjaan. 2.3. Berita Acara Serah Terima Pekerjaan yang ditandatangani oleh Direksi Pekerjaan dan PIHAK KEDUA serta ditandatangani oleh PIHAK PERTAMA. 2.4. Kuitansi 4 (empat) rangkap, bermeterai secukupnya. 2.5. e-faktur pajak. 2.6. Fotokopi Nomor Pokok Wajib Pajak (NPWP). 2.7. Fotokopi Pengukuhan Pengusaha Kena Pajak (PKP). 2.8. Fotokopi Perjanjian. 3. Pembayaran akan dilakukan oleh PIHAK PERTAMA dengan cara transfer ke rekening PIHAK KEDUA sebagaimana berikut: Nama Bank : [NAma Bank] No. Rekening : [No. Rekening] Atas Nama : [Nama Vendor] | C87: Jumlah Termin
C88: Persentase pembayaran termin pertama
C89: Kondisi/milestone pembayaran tahap 1
C90: Persentase pembayaran termin kedua
C91: Kondisi/milestone pembayaran tahap 2
C92: Nama Bank
C93: No. Rekening
C94: Nama Vendor
A95: ='Pemetaan Kontrak '!B34 -> Sanksi dan Denda | B95: 1. Sanksi administrasi yaitu surat peringatan tertulis dapat diberikan oleh PIHAK PERTAMA kepada PIHAK KEDUA dengan ketentuan sebagai berikut: 1.1 Apabila PIHAK KEDUA tidak melaksanakan pekerjaan sesuai dengan persyaratan-persyaratan dan ketentuan-ketentuan sebagaimana yang telah ditetapkan dalam Perjanjian ini, maka PIHAK PERTAMA akan memberikan Surat Peringatan Tertulis I (pertama) kepada PIHAK KEDUA mengenai pekerjaan yang tidak sesuai dengan persyaratan-persyaratan dan ketentuan- ketentuan yang telah ditetapkan tersebut. 1.2 Apabila dalam waktu [jumlah hari batas waktu setelah Surat Peringatan I] Hari Kalender dari Surat Peringatan I (pertama), PIHAK KEDUA belum melaksanakan pekerjaan sebagaimana dimaksud dalam surat peringatan tersebut baik sebagian maupun seluruhnya dan/ atau PIHAK KEDUA melakukan kesalahan atau kelalaian Kembali maka PIHAK PERTAMA akan memberikan Surat Peringatan II (kedua) kepada PIHAK KEDUA. 1.3 Apabila dalam waktu [jumlah hari batas waktu setelah Surat Peringatan II] Hari Kalender dari Surat Peringatan II (kedua), PIHAK KEDUA belum melaksanakan pekerjaan sebagaimana dimaksud dalam surat peringatan tersebut baik sebagian maupun seluruhnya dan/ atau PIHAK KEDUA melakukan kesalahan atau kelalaian Kembali maka PIHAK PERTAMA akan memberikan Surat Peringatan III (ketiga) kepada PIHAK KEDUA, dan PIHAK PERTAMA berhak melakukan klaim terhadap Jaminan Pelaksanaan dan tuntutan kompensasi sebagaimana diatur dalam Perjanjian ini serta mengakhiri Perjanjian secara sepihak. 1.4 PIHAK KEDUA yang menerima Surat Peringatan III (ketiga) dari PIHAK PERTAMA akan dimasukkan ke dalam daftar hitam (blacklist) Perusahaan. 2. Denda dapat dikenakan oleh PIHAK PERTAMA kepada PIHAK KEDUA dengan ketentuan sebagai berikut; 2.1 Apabila PIHAK KEDUA tidak memulai pelaksanaan Pekerjaan dalam waktu 14 (empat belas) hari setelah Tanggal Efektif Perjanjian, maka PIHAK KEDUA akan dikenakan denda sebesar Rp[nominal denda keterlambatan] untuk setiap hari keterlambatan memulai pekerjaan hingga pekerjaan tersebut dimulai oleh PIHAK KEDUA. 2.2 Apabila PIHAK KEDUA dalam melaksanakan pekerjaan melampaui batas waktu yang telah ditentukan sebagaimana diatur pada Perjanjian ini dan, maka PIHAK KEDUA akan dikenakan denda sebesar [minimal 1 ‰ (satu per mil) dari Nilai Perjanjian untuk setiap hari keterlambatan penyelesaian pekerjaan dengan maksimum [sebesar Jaminan Pelaksanaan/5% (lima persen)] dari Nilai Total Perjanjian. 2.3 Apabila PIHAK KEDUA tidak memenuhi besaran TKDN sebagaimana ditentukan dalam Perjanjian ini, maka PIHAK KEDUA akan dikendakan denda sebesar [persentase denda TKDN]% dari Nilai Total Perjanjian. 3. Pelaksanaan sanksi yang tersebut dalam ayat (1) di atas tidak menimbulkan hak bagi PIHAK KEDUA untuk menuntut kompensasi dalam bentuk apapun kepada PIHAK PERTAMA. | C95: Jumlah Hari Batas waktu setelah Surat Peringatan I
C96: Jumlah Hari Batas waktu setelah Surat Peringatan II
C97: Nominal denda keterlambatan
C98: Persentase denda TKDN
A99: ='Pemetaan Kontrak '!B35 -> Garansi | B99: 1. Pihak Kedua wajib menjamin bahwa Barang yang dijual dan diserahkan kepada Pihak Pertama adalah 100% (seratus persen) baru dan dalam keadaan baik, bebas dari cacat yang terlihat maupun yang tidak terlihat dan sesuai dengan spesifikasi teknis yang ditentukan dalam Kontrak ini. 2. Pihak Kedua menjamin garansi Barang selama [Masa Garansi] bulan terhitung sejak tanggal penyerahan Barang yang dibuktikan dengan diterbitkannya BASTB atas Kontrak Rinci (Masa Garansi). 3. Pihak Kedua wajib menerbitkan: (a) Surat/sertifikat garansi Barang sesuai Masa Garansi; dan (b) Surat Pernyataan Garansi Barang dengan format sebagaimana terlampir dalam Lampiran 9 Kontrak ini; sebagai salah satu kondisi diterbitkannya BASTB. 4. Surat Pernyataan Garansi Barang terkait akan menjamin berlakunya Masa Garansi yang mengatur kewajiban Pihak Kedua untuk memberikan perlindungan dan untuk menjamin penggantian Barang Rusak dan/atau Cacat Mutu kepada Pihak Pertama dan/atau Pengguna Kontrak Rinci jika terdapat kerusakan yang ditemukan setelah diterbitkannya BASTB maupun setelah berakhirnya Kontrak. 5. Pihak Kedua wajib untuk memberikan garansi dan menerbitkan surat/sertifikat garansi Barang sesuai Masa Garansi untuk setiap Barang Pengganti sebagaimana dimaksud dalam ayat (4) Pasal ini. 6. Pihak Kedua wajib untuk memberikan identitas pada setiap Barang dan memasang label garansi dengan mencantumkan Masa Garansi serta bulan dan tahun produksi termasuk bulan dan tahun berakhirnya Masa Garansi pada setiap produk Barang (bukan pada kemasannya). 7. Apabila dalam Masa Garansi terdapat Barang Rusak, maka Pihak Pertama dan/atau Pengguna Barang/Jasa akan memberitahukan secara tertulis kepada Pihak Kedua. 8. Pihak Kedua wajib mengganti Barang Rusak dengan Barang Pengganti yang sesuai dengan syarat yang ditentukan dalam Kontrak ini dalam jangka waktu dan prosedur yang ditentukan dalam surat pemberitahuan sebagaimana dimaksud ayat (7) Pasal ini, dan semua biaya yang diperlukan untuk penggantian Barang Rusak dimaksud menjadi beban dan tanggung jawab Pihak Kedua sesuai dengan hasil investigasi Barang Rusak. 9. Pihak Pertama dapat mengenakan sanksi daftar hitam (blacklist) kepada Pihak Kedua sebagaimana diatur dalam Pasal 30 dan Pasal 31 Kontrak ini apabila Pihak Kedua tidak melaksanakan kewajibannya dalam pasal ini. | C99: Masa garansi
A100: ='Pemetaan Kontrak '!B36 -> Integritas dan Good Corporate Governance | B100: 1. PARA PIHAK menyepakati tidak akan melakukan tindakan-tindakan yang mengakibatkan terjadinya ketidakwajaran dalam pelaksanaan Perjanjian ini termasuk namun tidak terbatas pada tindakan penipuan, penggelapan, pemerasan, kolusi, penyuapan, gratifikasi, korupsi, kecurangan, pemalsuan dan tindakan lain yang tidak sesuai dengan etika bisnis yang baik serta bertentangan dengan peraturan perundang-undangan yang berlaku termasuk mengenai pemberantasan tindak pidana korupsi, pencegahan dan pemberantasan tindak pidana pencucian uang, penerapan praktek Good Corporate Governance pada Badan Usaha Milik Negara (BUMN), termasuk peraturan yang mengatur mengenai Tata Kelola Anti Penyuapan yang berlaku di lingkungan PLN. 2. PARA PIHAK menyepakati bahwa Perjanjian ini dilaksanakan dengan itikad baik, tidak saling mempengaruhi baik langsung maupun tidak langsung guna memenuhi keinginannya, menerima serta bertanggungjawab atas segala keputusan yang ditetapkan sesuai dengan kesepakatan PARA PIHAK, menghindari serta mencegah terjadinya konflik kepentingan (conflict of interest), menghindari serta mencegah penyalahgunaan wewenang dan/ atau kolusi dengan tujuan untuk keuntungan pribadi, golongan atau pihak lain, dan tidak menerima, tidak menawarkan atau tidak menjanjikan untuk memberi atau menerima hadiah, imbalan berupa apa saja kepada siapapun yang diketahui atau patut diduga berkaitan dengan pelaksanaan Perjanjian ini. 3. PIHAK KEDUA menyatakan, menjamin dan berkomitmen kepada PIHAK PERTAMA, untuk mematuhi ketentuan hukum yang berlaku termasuk namun tidak terbatas pada, kebijakan anti-fraud dan tata Kelola anti-penyuapan di PLN seperti: a. Menerapkan 4 No’s: i. No bribery, menghindari suap menyuap dan pemerasan, ii. No gift, menghindari hadiah atau gratifikasi yang bertentangan dengan peraturan yang berlaku, iii. No kickback, menghindari komisi, tanda terima kasih baik dalam bentuk uang atau bentuk lainnya, iv. No luxurious hospitality, menghindari jamuan yang berlebihan; b. Menerapkan uji kelayakan berbasis integritas; c. Menghindari program sosialisasi system manajemen anti-penyuapan yang dilaksanakan PIHAK PERTAMA; d. Menandatangani dan melaksanakan pakta integritas; e. Melaporkan insiden fraud melalui Whistle Blowing System PLN. 4. PIHAK PERTAMA akan melakukan audit terkait tagihan pembayaan dan dokmen pembukuan serta pencatatan PIHAK KEDUA Ketika terdapat indikasi ketidakwajaran dari tagihan yang disampaikan oleh PIHAK KEDUA kepada PIHAK PERTAMA, dimana tujuan pelaksanaan audit tersebut untuk memastikan kesesuaian dengan ketentuan dalam Perjanjian. 5. Pelaksanaan audit sebagaimana dimaksud dalam ayat (4) pasal ini, dilakukan sebagai berikut: a. Atas biaya PLN; b. Dilakukan dengan pemberitahuan selambat-lambatnya [jumlah hari batas waktu pemberitahuan audit sebelum pelaksanaan] ([terbilang]) hari kalender sebelum pelaksanaan audit yang disampaikan pihak PIHAK PERTAMA kepada PIHAK KEDUA; c. Pelaksanaan audit dilaksanakan paling lambat dalam waktu [durasi pelaksanaan audit] ([terbilang]) hari kerja, dilanjutkan dengan pembuatan pelaporan audit oleh PIHAK PERTAMA paling lambat dalam [jumlah hari batas waktu pembuatan laporan audit] ([terbilang]) hari kerja; d. Penyelesaian pembayaran (settlement/ adjustment) dilakukan paling lambat [jumlah hari batas waktu penyelesaian pembayaran setelah audit] ([terbilang]) hari kalender setelah PIHAK PERTAMA memaparkan laporan hasil audit kepada PIHAK KEDUA; e. PIHAK PERTAMA dapat menunjuk pihak lain untuk melakukan audit; f. PIHAK KEDUA wajib mengizinkan perwakilan PIHAK PERTAMA dan menyediakan dokumen dan data yang diperlukan; g. Permintaan dan penyampaian dokumen dan data audit dilaksanakan pada jam kerja PIHAK KEDUA; h. Apabila terdapat Kerjasama antara PIHAK KEDUA dengan Pihak Ketiga yang berkaitan dengan Pelaksanaan Perjanjian ini, maka PIHAK KEDUA wajib memastikan dan menuangkan ketentuan mengenai Hak Akses PIHAK PERTAMA terhadap dokumen dan data milik Pihak Ketiga dalam Kontrak antara PIHAK KEDUA dengan Pihak Ketiga tersebut. i. PARA PIHAK termasuk perwakilannya, akan menjaga kerahasiaan informasi non-publik yang diperoleh dari pelaksanaan audit tersebut. | C100: jumlah hari Batas waktu pemberitahuan audit sebelum pelaksanaan
C101: Durasi pelaksanaan audit
C102: jumlah hari Batas waktu pembuatan laporan audit
C103: Batas waktu penyelesaian pembayaran setelah audit
A104: ='Pemetaan Kontrak '!B37 -> Keselamatan Kesehatan Kerja dan Lingkungan | B104: 1. Kegiatan Pencegahan Terjadinya Kecelakaan Kerja 1.1 Pencegahan Kondisi Berbahaya (Unsafe Condition) PIHAK KEDUA wajib melakukan pengendalian teknis terhadap adanya kondisi berbahaya (unsafe condition) pada tempat-tempat kerja, antara lain: a. PIHAK KEDUA wajib mematuhi peraturan Keselamatan dan Kesehatan Kerja yang berlaku di lingkungan PIHAK PERTAMA; b. PIHAK KEDUA wajib melapor setiap akan memulai pekerjaan dan selesai pekerjaan kepada Pengawas Pekerjaan di lokasi/ unit PIHAK KEDUA tersebut melaksanakan pekerjaan; c. PIHAK KEDUA wajib memiliki dan menerapkan Standing Operation Procedure (SOP) untuk setiap pekerjaan; d. PIHAK KEDUA wajib menyediakan peralatan kerja dan APD sesuai standar bagi tenaga kerjanya pada pelaksanaan pekerjaan yang berpotensi bahaya; e. PIHAK KEDUA wajib melakukan identifikasi bahaya, penilaian risiko dan pengendalian risiko (IBPPR) pada tempat kerja yang berpotensi bahaya; f. PIHAK KEDUA wajib membuat Job Safety Analysis (JSA) dan Ijin Kerja (Working Permit) pada setiap pelaksanaan yang berpotensi bahaya; g. PIHAK KEDUA wajib melakukan pemeriksaan Kesehatan kerja bagi tenaga kerjanya yang bekerja pada pekerjaan yang berpotensi; h. PIHAK KEDUA dilarang mempekerjakan masyarakat umum/ buruh harian lepas yang tidak memiliki hubungan Kontraktual dengan PIHAK KEDUA. 1.2 Pencegahan Tindakan Berbahaya (Unsafe Action) PIHAK KEDUA wajib melakukan pengendalian personel terhadap perilaku berbahaya (Unsafe Act) dari Pelaksana dan Pengawas Pekerjaan, antara lain: a. PIHAK KEDUA wajib menunjuk dan menetapkan Pengawas Pekerjaan/ Pengawas K2/K3 yang memiliki kompetensi di bidang pekerjaannya; b. PIHAK KEDUA wajib memasang LOTO (Lock Out Tag Out) pada saat pelaksanaan pekerjaan yang berpotensi berbahaya; c. Pelaksana Pekerjaan dari PIHAK KEDUA wajib menggunakan peralatan kerja dan APD sesuai standar pada pelaksanaan pekerjaan yang berpotensi bahaya; d. PIHAK KEDUA wajib melakukan pengawasan terhadap perilaku tenaga kerjanya yang membahayakan bagi diri sendiri maupun orang lain, yang dapat menyebabkan terjadinya kecelakaan kerja; e. PIHAK KEDUA wajib memberikan petunjuk dan arahan keselamatan (safety briefing) kepada Pelaksana Pekerjaan dan Pengawas Pekerjaan sebelum melaksanakan pekerjaan yang berpotensi bahaya. 2. Sertifikasi/ Pendidikan & Pelatihan a. PIHAK KEDUA wajib melakukan sertifikasi kompetensi bagi Pengawas Pekerjaan, Pelaksana Pekerjaan dan tenaga teknik lainnya sesuai dengan bidang pekerjaannya; b. PIHAK KEDUA wajib memiliki Tenaga Kerja Pengawas K2/ K3 yang bersertifikasi kompetensi; c. PIHAK KEDUA wajib memberikan petunjuk dan arahan keselamatan (safety briefing) kepada Pelaksana Pekerjaan dan tenaga Teknik lainnya sesuai dengan bidang pekerjaanya. 3. Sanksi a. Apabila terjadi kecelakaan kerja akibat kelalaian PIHAK KEDUA dalam penerapan Sistem Manajemen Keselamatan dan Kesehatan Kerja maka PIHAK KEDUA bertanggung jawab secara penuh untuk menyelesaikan segala permasalahan yang ditimbulkan akibat kecelakaan tersebut. b. Apabila terjadi kecelakaan kerja akibat kelalaian Pelaksana Pekerja dari PIHAK KEDUA, maka Pelaksana Pekerjaan tersebut bertanggung jawab secara penuh atas akibat kecelakaan tersebut. c. Apabila terjadi kecelakaan kerja akibat kelalaian PIHAK KEDUA dalam penerapan Sistem Manajemen Keselamatan dan Kesehatan Kerja, maka PIHAK PERTAMA berhak mengevaluasi, memutus Perjanjian barang dan jasa yang sedang berlangsung secara sepihak serta memasukkan PIHAK KEDUA tersebut pada Daftar Hitam (black list) perusahaan. | C104: -
...

Sheet PLTHidro
B2: Identifier Perjanjian | E2: Para pihak
B3: Pendahuluan | E3: Latar belakang, maksud
A4: Pasal 1 | B4: Definisi
A5: Pasal 2 | B5: Proyek | C5: 2.1 | D5: Maksud dan Tujuan | E5: maksud dan tujuan perjanjian
C6: 2.2 | D6: Proyek | E6: terdiri atas
C7: 2.3 | D7: Jangka Waktu Perjanjian
A8: Pasal 3 | B8: Keberlakuan Perjanjian dan Syarat Tangguh | C8: 3.1 | D8: Tanggal Efektif Perjanjian
C9: 3.2 | D9: Tanggal Pembiayaan
A10: Pasal 4 | B10: Pelaksanaan Proyek | C10: 4.1 | D10: Tanggung Jawab Penjual
C11: 4.2 | D11: Tanggung Jawab PLN
C12: 4.3 | D12: Persetujuan PLN
C13: 4.4 | D13: Perubahan terhadap Jadwal Kejadian Penting
C14: 4.5 | D14: Kerugian Karena Keterlambatan
C15: 4.6 | D15: Jaminan Pelaksanaan
C16: 4.7 | D16: Peristiwa Pemicu | E16: Jika salah satu Pihak memandang bahwa suatu Peristiwa Pemicu telah terjadi yang akan mengakibatkan Biaya atau Penghematan
A17: Pasal 5 | B17: Pembangunan Proyek | C17: 5.1 | D17: Tanggung Jawab Pembangunan
C18: 5.2 | D18: Hak Akses
C19: 5.3 | D19: Sistem Jaringan Listrik PLN
C20: 5.4 | D20: Izin, Lisensi, dan lain-lain
C21: 5.5 | D21: Gambar, Hasil Pengujian, dan lain-lain
C22: 5.6 | D22: Titik Interkoneksi dan Fasilitas-fasilitas Interkoneksi Listrik | E22: umum, rancangan antarmuka
C23: 5.7 | D23: Fasilitas Khusus
C24: 5.8 | D24: Lahan untuk Lokasi dan Lokasi Fasilitas Khusus
A25: Pasal 6 | B25: Start-Up dan Komisioning | C25: 6.1 | D25: Pembangkitan Energi Awal
C26: 6.2 | D26: Sinkronisasi Awal Dengan Sistem Jaringan Listrik PLN
C27: 6.3 | D27: Komisioning dan Pengujian
C28: 6.4 | D28: Verifikasi TKDN dan Sertifikat TKDN
A29: Pasal 7 | B29: Pengoperasian dan Pemeliharaan Pembangkit | C29: 7.1 | D29: Pengoperasian, Pemeliharaan dan Perbaikan
C30: 7.2 | D30: Persyaratan Lingkungan
C31: 7.3 | D31: Koordinasi dengan PLN
C32: 7.4 | D32: Jadwal Pengujian
A33: Pasal 8 | B33: Jual Beli Tenaga Listrik | C33: 8.1 | D33: Penjualan dan Pembelian
C34: 8.2 | D34: Program Pengoperasian Pengiriman Beban
C35: 8.3 | D35: Rencana Pasokan Energi dan Debit Air Rencana
C36: 8.4 | D36: ECEm
C37: 8.5 | D37: Hak Untuk Pembatasan Pengiriman Energi
C38: 8.6
